{"name":"Вайль Петр, Генис Александр - Родная речь. Уроки изящной словесности [Игорь Князев, 2022, 64 kbps, MP3]","category":"Художественная литература","subcategory":"[Аудио] Русская литература","torrentSize":"201.5 MB","torrentLink":"magnet:?xt=urn:btih:27D1809B0F45FCCE0A7839705FAF845CB3CEAE57&tr=http%3A%2F%2Fbt.t-ru.org%2Fann%3Fmagnet","coverImageUrl":"https://i117.fastpic.org/big/2022/0421/00/bcc711b575e3e1227276c6e4a73ede00.jpg","URL":"https://rutracker.org/forum/viewtopic.php?t=6205049"}
{"name":"Гергенрёдер Игорь - Комбинации против Хода Истории. Сборник повестей [Владимир Князев, 2021, 192 kbps, MP3]","category":"Художественная литература","subcategory":"[Аудио] Русская литература","torrentSize":"817.5 MB","torrentLink":"magnet:?xt=urn:btih:48C6CFD40140E0E6C7C2DE75B9B21A2BC1A4A710&tr=http%3A%2F%2Fbt2.t-ru.org%2Fann%3Fmagnet","coverImageUrl":"https://i115.fastpic.org/big/2021/0727/e1/b33974b3704acfb2edca729ca8aa32e1.jpg","URL":"https://rutracker.org/forum/viewtopic.php?t=6086750"}
{"name":"Список произведений А.Чехова и О'Генри, раздающихся в этом разделе. Убедительная просьба при создании раздачи, писать мне в ЛС","category":"Художественная литература","subcategory":"[Аудио] Русская литература","URL":"https://rutracker.org/forum/viewtopic.php?t=392913"}
{"name":"Быков Дмитрий - Прощай, кукушка (сборник) [Игорь Князев, 2014, 144 kbps, MP3]","category":"Художественная литература","subcategory":"[Аудио] Русская литература","torrentSize":"332.9 MB","torrentLink":"magnet:?xt=urn:btih:F404603B76C8E5A9533F6E249A19456F89BDEAB3&tr=http%3A%2F%2Fbt3.t-ru.org%2Fann%3Fmagnet","coverImageUrl":"https://i116.fastpic.org/big/2022/0215/f0/ccdee1be04141f56674aabd41347b1f0.jpg","URL":"https://rutracker.org/forum/viewtopic.php?t=6179496"}
{"name":"Лукаш Иван - Сны Петра [Ильин Р., (ЛИ), 2022, 128 kbps, MP3]","category":"Художественная литература","subcategory":"[Аудио] Русская литература","torrentSize":"304.3 MB","torrentLink":"magnet:?xt=urn:btih:B2665FFCB9125BC2B3A72976510E298ECB2C5739&tr=http%3A%2F%2Fbt3.t-ru.org%2Fann%3Fmagnet","coverImageUrl":"https://i116.fastpic.org/big/2022/0101/80/8141f5b253c54930f950be6b9fa69f80.jpg","URL":"https://rutracker.org/forum/viewtopic.php?t=6158202"}
{"name":"Вайль Петр, Генис Александр - Родная речь. Уроки изящной словесности [Игорь Князев, 2022, 64 kbps, MP3]","category":"Художественная литература","subcategory":"[Аудио] Русская литература","torrentSize":"201.5 MB","torrentLink":"magnet:?xt=urn:btih:27D1809B0F45FCCE0A7839705FAF845CB3CEAE57&tr=http%3A%2F%2Fbt.t-ru.org%2Fann%3Fmagnet","coverImageUrl":"https://i117.fastpic.org/big/2022/0421/00/bcc711b575e3e1227276c6e4a73ede00.jpg","URL":"https://rutracker.org/forum/viewtopic.php?t=6205049"}
{"name":"Бек Александр - Волоколамское шоссе [Юрова Лариса, 2020, 96 kbps, MP3]","category":"Художественная литература","subcategory":"[Аудио] Русская литература","torrentSize":"873.8 MB","torrentLink":"magnet:?xt=urn:btih:D28C3F0EFF7EA4676B059266B4E1B1443AC22D92&tr=http%3A%2F%2Fbt.t-ru.org%2Fann%3Fmagnet","coverImageUrl":"https://i.ibb.co/PWcXMQQ/Bek-A-Volokolamskoe-shosse-Yurova-K.jpg","URL":"https://rutracker.org/forum/viewtopic.php?t=5916416"}
{"name":"Бек Александр - Волоколамское шоссе [Герасимов Вячеслав, 2015 г., 96 kbps, MP3]","category":"Художественная литература","subcategory":"[Аудио] Русская литература","torrentSize":"977.5 MB","torrentLink":"magnet:?xt=urn:btih:7600B75B968DF05E8692EE2EE9073BAA692CD26E&tr=http%3A%2F%2Fbt3.t-ru.org%2Fann%3Fmagnet","coverImageUrl":"http://s020.radikal.ru/i722/1505/4a/26fa0616e2e8.jpg","URL":"https://rutracker.org/forum/viewtopic.php?t=5002413"}
{"name":"Список произведений А.Чехова и О'Генри, раздающихся в этом разделе. Убедительная просьба при создании раздачи, писать мне в ЛС","category":"Художественная литература","subcategory":"[Аудио] Русская литература","URL":"https://rutracker.org/forum/viewtopic.php?t=392913"}
{"name":"Шишкин Михаил - Венерин волос [Александр Аравушкин, 2021, 56 kbps, MP3]","category":"Художественная литература","subcategory":"[Аудио] Русская литература","torrentSize":"413.2 MB","torrentLink":"magnet:?xt=urn:btih:6579DCD640BED52D68456172315BA3D36D9F8501&tr=http%3A%2F%2Fbt3.t-ru.org%2Fann%3Fmagnet","coverImageUrl":"https://i120.fastpic.org/big/2022/1002/52/7ecf2f168c150f6fc02ca211f47f5e52.jpg","URL":"https://rutracker.org/forum/viewtopic.php?t=6265079"}
{"name":"Бек Александр - Волоколамское шоссе[Герасимов Вячеслав, 2015 г., 128 kbps, 44 kHz, Моно, MP3]","category":"Художественная литература","subcategory":"[Аудио] Русская литература","torrentSize":"1.28 GB","torrentLink":"magnet:?xt=urn:btih:C1C4ECB665D7FA7BDD8318D67A7ECF2408677355&tr=http%3A%2F%2Fbt3.t-ru.org%2Fann%3Fmagnet","coverImageUrl":"http://i58.fastpic.ru/big/2015/0512/76/dbf28ae838f35609bdab0bafcf39a676.jpg","URL":"https://rutracker.org/forum/viewtopic.php?t=5004624"}
{"name":"Илья Ильф, Евгений Петров - Одноэтажная Америка. Рассказы [Владимир Солдатов, 2021, 128 kbps, MP3]","category":"Художественная литература","subcategory":"[Аудио] Русская литература","torrentSize":"967.1 MB","torrentLink":"magnet:?xt=urn:btih:ACF391E28D18A021F0D2A987F2E95566393C0477&tr=http%3A%2F%2Fbt4.t-ru.org%2Fann%3Fmagnet","coverImageUrl":"https://i120.fastpic.org/big/2022/1023/4e/89f5fad4eb7589dbf206061031cb154e.jpg","URL":"https://rutracker.org/forum/viewtopic.php?t=6274410"}
{"name":"Гончаров Иван - Обломов [Александр Дунин, 2021, 128 kbps, MP3]","category":"Художественная литература","subcategory":"[Аудио] Русская литература","torrentSize":"1.29 GB","torrentLink":"magnet:?xt=urn:btih:407589723FD11219A45F1661D465A5D2CE885F00&tr=http%3A%2F%2Fbt3.t-ru.org%2Fann%3Fmagnet","coverImageUrl":"https://i116.fastpic.org/big/2021/1110/68/5935f5cfc9e645040056bc849695a568.jpg","URL":"https://rutracker.org/forum/viewtopic.php?t=6134896"}
{"name":"Пелевин Виктор - KGBT+ (КГБТ+) [Максим Суханов, FEDUK, 2022, 128 kbps, MP3]","category":"Художественная литература","subcategory":"[Аудио] Русская литература","torrentSize":"867.8 MB","torrentLink":"magnet:?xt=urn:btih:CFD3C4009077A4136315B3B6D12A449B8B62E405&tr=http%3A%2F%2Fbt2.t-ru.org%2Fann%3Fmagnet","coverImageUrl":"https://i120.fastpic.org/big/2022/0930/91/cd4290da6a13e0dde8fa1e02004ad391.jpg","URL":"https://rutracker.org/forum/viewtopic.php?t=6264536"}
{"name":"Алексей Николаевич Толстой - Хождение по мукам [Иван Литвинов, 2006 г., 128 kbps, MP3]","category":"Художественная литература","subcategory":"[Аудио] Русская литература","torrentSize":"2.69 GB","torrentLink":"magnet:?xt=urn:btih:0AF45B7FE98E8B7E0EC54DCC0177E9F7FDCAD44A&tr=http%3A%2F%2Fbt3.t-ru.org%2Fann%3Fmagnet","coverImageUrl":"http://i77.fastpic.ru/big/2016/0503/37/c6153e61c024405cb4821797c7698037.jpg","URL":"https://rutracker.org/forum/viewtopic.php?t=5219080"}
{"name":"Гуляева Ольга - Как умирала Вера [Михаил Мурзаков, 2018, 256 kbps, MP3]","category":"Художественная литература","subcategory":"[Аудио] Русская литература","torrentSize":"885.7 MB","torrentLink":"magnet:?xt=urn:btih:80F52512B2ED89CD5E99B7FF301070816FE7EA6A&tr=http%3A%2F%2Fbt4.t-ru.org%2Fann%3Fmagnet","coverImageUrl":"https://d.radikal.ru/d16/1805/b2/eb606adb85b9.jpg","URL":"https://rutracker.org/forum/viewtopic.php?t=5562643"}
{"name":"Елизаров Михаил — Земля [Александр Зачиняев, 2019, 128 kbps, MP3]","category":"Художественная литература","subcategory":"[Аудио] Русская литература","torrentSize":"1.36 GB","torrentLink":"magnet:?xt=urn:btih:A3940ACB998F623DE19F8A5CC00025DA867A4EB8&tr=http%3A%2F%2Fbt3.t-ru.org%2Fann%3Fmagnet","coverImageUrl":"https://i111.fastpic.ru/big/2020/0118/19/eb431b43e83ddec4131ca465cb4dca19.jpg","URL":"https://rutracker.org/forum/viewtopic.php?t=5820846"}
{"name":"Богатырёва Елена - Сногсшибательная женщина [Ларионова Людмила, 2012 г. 128 kbps, MP3]","category":"Художественная литература","subcategory":"[Аудио] Русская литература","torrentSize":"319.7 MB","torrentLink":"magnet:?xt=urn:btih:AA4F15C178F4B71D9894FBF6D4992E01FBBE2362&tr=http%3A%2F%2Fbt4.t-ru.org%2Fann%3Fmagnet","coverImageUrl":"http://img-fotki.yandex.ru/get/6205/110047830.2c/0_66e3f_7223d2d4_L.jpg","URL":"https://rutracker.org/forum/viewtopic.php?t=4031043"}
{"name":"Леонтьев Борис - Триумф великого комбинатора, или Возвращение Остапа Бендера [Григорий Шевчук, 2006, 64 Кбит/сек, 44 кГц, моно]","category":"Художественная литература","subcategory":"[Аудио] Русская литература","torrentSize":"271.7 MB","torrentLink":"magnet:?xt=urn:btih:E39DDB54ACD5B855D393C589A8D27B0F819EF7A2&tr=http%3A%2F%2Fbt2.t-ru.org%2Fann%3Fmagnet","coverImageUrl":"http://i3.fastpic.ru/big/2009/1023/d4/c881e652a24e53041e5d7507cadf87d4.jpg","URL":"https://rutracker.org/forum/viewtopic.php?t=1654391"}
{"name":"Иванов Алексей - Сердце Пармы [Сергей Гармаш, 2021, 112 kbps, MP3]","category":"Художественная литература","subcategory":"[Аудио] Русская литература","torrentSize":"1.29 GB","torrentLink":"magnet:?xt=urn:btih:E3B458EB272AE5B7A7FA754BB6DDC96358B04F17&tr=http%3A%2F%2Fbt4.t-ru.org%2Fann%3Fmagnet","coverImageUrl":"https://i120.fastpic.org/big/2022/0822/1f/5768ad36b36a740af46be56a2883761f.jpg","URL":"https://rutracker.org/forum/viewtopic.php?t=6249796"}
{"name":"Лесков Николай - Праведники [Герасимов Вячеслав, 2007, 128 kbps, MP3]","category":"Художественная литература","subcategory":"[Аудио] Русская литература","torrentSize":"496.8 MB","torrentLink":"magnet:?xt=urn:btih:FFF5AF2C384F4BB5D3FEFAB57E8AED52DB44A770&tr=http%3A%2F%2Fbt.t-ru.org%2Fann%3Fmagnet","coverImageUrl":"https://i116.fastpic.org/big/2022/0214/96/93d44c5119ce3490bde7abfae454b096.jpg","URL":"https://rutracker.org/forum/viewtopic.php?t=6178977"}
{"name":"Савинков Борис - Конь бледный + лекция Дмитрия Быкова [Дмитрий Быков, 2020, 96 kbps, MP3]","category":"Художественная литература","subcategory":"[Аудио] Русская литература","torrentSize":"140.2 MB","torrentLink":"magnet:?xt=urn:btih:9DA28D393174DF6113D01C6A341009AE8D26B9F1&tr=http%3A%2F%2Fbt2.t-ru.org%2Fann%3Fmagnet","coverImageUrl":"https://i120.fastpic.org/big/2022/1014/83/567f614f8a491abb4eda3a108b4dc983.jpg","URL":"https://rutracker.org/forum/viewtopic.php?t=6270111"}
{"name":"Войнович Владимир - Малиновый пеликан [Сергей Чонишвили, 2018, 128 kbps, MP3]","category":"Художественная литература","subcategory":"[Аудио] Русская литература","torrentSize":"455.2 MB","torrentLink":"magnet:?xt=urn:btih:931B52979FFEE36EF34E02BA364BC1E65737B8D2&tr=http%3A%2F%2Fbt3.t-ru.org%2Fann%3Fmagnet","coverImageUrl":"https://i120.fastpic.org/big/2022/1018/74/39bc00a5c6f8872bda8251ebd1b82174.jpg","URL":"https://rutracker.org/forum/viewtopic.php?t=6272005"}
{"name":"Толстой Алексей - Хождение по мукам + лекция Дмитрия Быкова [Дмитрий Быков, 2022, 96 kbps, MP3]","category":"Художественная литература","subcategory":"[Аудио] Русская литература","torrentSize":"526.8 MB","torrentLink":"magnet:?xt=urn:btih:0C0E730A23B4298431A704ED403D11C79E04C70F&tr=http%3A%2F%2Fbt3.t-ru.org%2Fann%3Fmagnet","coverImageUrl":"https://i120.fastpic.org/big/2022/1021/98/5f58a4a93911152af76ac63d7d05ff98.jpg","URL":"https://rutracker.org/forum/viewtopic.php?t=6273330"}
{"name":"Попов Валерий - Безумное плавание. Водная феерия + лекция Дмитрия Быкова [Дмитрий Быков, 2021, 96 kbps, MP3]","category":"Художественная литература","subcategory":"[Аудио] Русская литература","torrentSize":"200.9 MB","torrentLink":"magnet:?xt=urn:btih:62DD3AF30998B55A67DB36EDA825D9183539D363&tr=http%3A%2F%2Fbt.t-ru.org%2Fann%3Fmagnet","coverImageUrl":"https://i120.fastpic.org/big/2022/1018/34/73edb78b0218ff92f4340bf40f32ea34.jpg","URL":"https://rutracker.org/forum/viewtopic.php?t=6272003"}
{"name":"Достоевский Федор - Дядюшкин сон. Крокодил. Скверный анекдот [Владимир Самойлов, 2010, 128 kbps, MP3]","category":"Художественная литература","subcategory":"[Аудио] Русская литература","torrentSize":"604.9 MB","torrentLink":"magnet:?xt=urn:btih:FF01C8ECBF33E9218BFEBF0F97E7FB7D211C602D&tr=http%3A%2F%2Fbt3.t-ru.org%2Fann%3Fmagnet","coverImageUrl":"https://i120.fastpic.org/big/2022/1022/78/6127e84f06382fb5ced9502d279c0178.jpg","URL":"https://rutracker.org/forum/viewtopic.php?t=6273845"}
{"name":"Горький Максим - Макар Чудра. Челкаш. Старуха Изергиль [Дмитрий Оргин, 2014, 96 kbps, MP3]","category":"Художественная литература","subcategory":"[Аудио] Русская литература","torrentSize":"135.3 MB","torrentLink":"magnet:?xt=urn:btih:611F0784C691DE21004C7DA401610FD5CE8397FE&tr=http%3A%2F%2Fbt4.t-ru.org%2Fann%3Fmagnet","coverImageUrl":"https://i120.fastpic.org/big/2022/1022/b4/11eae26697914ef3d52edb332013b2b4.jpg","URL":"https://rutracker.org/forum/viewtopic.php?t=6273843"}
{"name":"Сорокин Владимир - Сахарный кремль [Николай Кобзев, (ЛИ), 2017, 128-192 kbps, MP3]","category":"Художественная литература","subcategory":"[Аудио] Русская литература","torrentSize":"399.1 MB","torrentLink":"magnet:?xt=urn:btih:D127527B5D17E32643DE4424933E69D4FFBFFA00&tr=http%3A%2F%2Fbt2.t-ru.org%2Fann%3Fmagnet","coverImageUrl":"https://i116.fastpic.org/big/2021/1208/e4/871321214d209379b7bbba88d138fee4.jpg","URL":"https://rutracker.org/forum/viewtopic.php?t=6147780"}
{"name":"Ремизов Виктор - Вечная мерзлота [Сергей Чонишвили, 2022, 64 kbps, MP3]","category":"Художественная литература","subcategory":"[Аудио] Русская литература","torrentSize":"1012.6 MB","torrentLink":"magnet:?xt=urn:btih:9E8BB6242127E87CBBA35112922658A88BCADDBE&tr=http%3A%2F%2Fbt2.t-ru.org%2Fann%3Fmagnet","coverImageUrl":"https://i116.fastpic.org/big/2022/0206/95/3ed23b8e3cce24ab068a6165c806d495.jpg","URL":"https://rutracker.org/forum/viewtopic.php?t=6175245"}
{"name":"Акунин Борис - Семейный альбом 05, Медвежатница [Александр Клюквин, 2022, 128 kbps, MP3]","category":"Художественная литература","subcategory":"[Аудио] Русская литература","torrentSize":"442 MB","torrentLink":"magnet:?xt=urn:btih:54C228B98AD98E1293D04863B2600CB3D6315B23&tr=http%3A%2F%2Fbt2.t-ru.org%2Fann%3Fmagnet","coverImageUrl":"https://i120.fastpic.org/big/2022/0810/b6/899270ab8a7067990493767f0724c0b6.jpg","URL":"https://rutracker.org/forum/viewtopic.php?t=6245089"}
{"name":"ЧеширКо Евгений - Дневник Домового. Рассказы с чердака [Смирнов Геннадий, 2020, 128 kbps, MP3]","category":"Художественная литература","subcategory":"[Аудио] Русская литература","torrentSize":"406.7 MB","torrentLink":"magnet:?xt=urn:btih:4831031A05C7505EB3AE1B8FB699A94CDC5BDE4B&tr=http%3A%2F%2Fbt3.t-ru.org%2Fann%3Fmagnet","coverImageUrl":"https://b.radikal.ru/b37/2001/df/305d014da395.jpg","URL":"https://rutracker.org/forum/viewtopic.php?t=5835223"}
{"name":"Пушкин Александр - Капитанская дочка [Александр Котов, 2010, 96 kbps, MP3]","category":"Художественная литература","subcategory":"[Аудио] Русская литература","torrentSize":"215.2 MB","torrentLink":"magnet:?xt=urn:btih:57BF21EFC0A7B0698CAB58CF4272332436D9D890&tr=http%3A%2F%2Fbt.t-ru.org%2Fann%3Fmagnet","coverImageUrl":"https://i120.fastpic.org/big/2022/1021/6c/8f4408446e0a3c2bd4cfbbf382d8756c.jpg","URL":"https://rutracker.org/forum/viewtopic.php?t=6273336"}
{"name":"Тургенев Иван - Му-му [Сергей Рост, 2010, 128 kbps, MP3]","category":"Художественная литература","subcategory":"[Аудио] Русская литература","torrentSize":"65.5 MB","torrentLink":"magnet:?xt=urn:btih:6D2ACFD647EE27AFE8CE386EF32C3B66EC5AE097&tr=http%3A%2F%2Fbt3.t-ru.org%2Fann%3Fmagnet","coverImageUrl":"https://i120.fastpic.org/big/2022/1021/53/1c089940d20c0ceac0fa24b2d871a253.jpg","URL":"https://rutracker.org/forum/viewtopic.php?t=6273332"}
{"name":"Пелевин Виктор - TRANSHUMANISM INC. (Трансгуманизм Inc.) (Трансгуманизм) [Максим Суханов, Ксения Собчак, Галина Юзефович, 2021, 128 kbps, MP3]","category":"Художественная литература","subcategory":"[Аудио] Русская литература","torrentSize":"927.3 MB","torrentLink":"magnet:?xt=urn:btih:84923210E2C566DF97CD90D7F7DA10B5EEEAC413&tr=http%3A%2F%2Fbt4.t-ru.org%2Fann%3Fmagnet","coverImageUrl":"https://i1.imageban.ru/out/2021/08/27/34bb1ba9baee083baa092fcab23052f2.jpg","URL":"https://rutracker.org/forum/viewtopic.php?t=6100929"}
{"name":"Ефремов Иван - Юрта Ворона. Избранные рассказы [Вадим Максимов, 2016 г., 128 kbps, MP3]","category":"Художественная литература","subcategory":"[Аудио] Русская литература","torrentSize":"345.9 MB","torrentLink":"magnet:?xt=urn:btih:879E23D4D7366D70B504F6F01F32DD962EBB3BB7&tr=http%3A%2F%2Fbt.t-ru.org%2Fann%3Fmagnet","coverImageUrl":"http://i74.fastpic.ru/big/2016/0402/5b/de8ddcaa14404222a8eb09755a735b5b.jpg","URL":"https://rutracker.org/forum/viewtopic.php?t=5200910"}
{"name":"Арсеньева Елена - Сага о семье Русановых 04. Несбывшаяся весна [Савицкий Николай, 2013, 96 kbps, MP3]","category":"Художественная литература","subcategory":"[Аудио] Русская литература","torrentSize":"804.1 MB","torrentLink":"magnet:?xt=urn:btih:AE3C80B7CD64D370DB1007FF562CDB902A53D08F&tr=http%3A%2F%2Fbt3.t-ru.org%2Fann%3Fmagnet","coverImageUrl":"http://i48.fastpic.ru/big/2013/0508/43/9852144e5709a5786ac06a03f8b12d43.jpg","URL":"https://rutracker.org/forum/viewtopic.php?t=4433993"}
{"name":"Куприн Александр - Штабс-капитан Рыбников [Александр Бордуков, 2019, 112 kbps, MP3]","category":"Художественная литература","subcategory":"[Аудио] Русская литература","torrentSize":"64.9 MB","torrentLink":"magnet:?xt=urn:btih:9620994614795C5643D1AA4D8B22B754150DF651&tr=http%3A%2F%2Fbt.t-ru.org%2Fann%3Fmagnet","coverImageUrl":"https://i120.fastpic.org/big/2022/1018/33/1a0c756f2d3005ce717c89e4e2aecd33.jpg","URL":"https://rutracker.org/forum/viewtopic.php?t=6272007"}
{"name":"Куприн Александр - Поединок [Кузнецов Всеволод, 2019, 64 kbps, MP3]","category":"Художественная литература","subcategory":"[Аудио] Русская литература","torrentSize":"257.2 MB","torrentLink":"magnet:?xt=urn:btih:78BF04EFEDADAADCD2278A3300177991612008AA&tr=http%3A%2F%2Fbt2.t-ru.org%2Fann%3Fmagnet","coverImageUrl":"https://i120.fastpic.org/big/2022/0531/54/fd124c294ac687db31cfbcec8c401154.jpg","URL":"https://rutracker.org/forum/viewtopic.php?t=6220816"}
{"name":"Алешковский Пётр – Секретики [Алешковский Пётр, 2020, 128 kbps, MP3]","category":"Художественная литература","subcategory":"[Аудио] Русская литература","torrentSize":"540.9 MB","torrentLink":"magnet:?xt=urn:btih:3E1439988C831644E79B837FEE85260F10B4E8F5&tr=http%3A%2F%2Fbt2.t-ru.org%2Fann%3Fmagnet","coverImageUrl":"https://i5.imageban.ru/out/2020/09/17/26fd0b5c44ada5e5e0beebf41645158e.jpg","URL":"https://rutracker.org/forum/viewtopic.php?t=5942857"}
{"name":"Миронов Иван - Красный, жёлтый, зелёный [Сергей Локтионов, Татьяна Николашина, (ЛИ), 2019, 128 kbps, MP3]","category":"Художественная литература","subcategory":"[Аудио] Русская литература","torrentSize":"28.3 MB","torrentLink":"magnet:?xt=urn:btih:0E9D2A1CC3D68CF9C680CFB0140D1F2149AFF711&tr=http%3A%2F%2Fbt2.t-ru.org%2Fann%3Fmagnet","coverImageUrl":"https://i87.fastpic.ru/big/2019/1012/a9/92357ca75cac976c2929476928cdc1a9.jpg","URL":"https://rutracker.org/forum/viewtopic.php?t=5790430"}
{"name":"Миронов Иван - Замурованные: Хроники Кремлевского централа [В.А. Никитин и И.Б. Миронов, 2010 г., 128/256, MP3]","category":"Художественная литература","subcategory":"[Аудио] Русская литература","torrentSize":"675.2 MB","torrentLink":"magnet:?xt=urn:btih:462A2915A869BD2B45CEA7D37C3E8B15AA111C3B&tr=http%3A%2F%2Fbt4.t-ru.org%2Fann%3Fmagnet","URL":"https://rutracker.org/forum/viewtopic.php?t=3290935"}
{"name":"Шмелёв Иван - Старый Валаам [Георгий Корольчук, 2010 г., 128 kbps, MP3]","category":"Художественная литература","subcategory":"[Аудио] Русская литература","torrentSize":"280.1 MB","torrentLink":"magnet:?xt=urn:btih:A9FE4A9A2FFB9EE624CAE8CF1D71F32E11C3A4C5&tr=http%3A%2F%2Fbt2.t-ru.org%2Fann%3Fmagnet","coverImageUrl":"http://i14.fastpic.ru/big/2010/1229/0e/0d9cb4b4d5dd5542dd772b4dc25d230e.jpg","URL":"https://rutracker.org/forum/viewtopic.php?t=3342119"}
{"name":"Андрей Платонов - Избранные произведения [Георгий Корольчук, 2005, 80 kbps]","category":"Художественная литература","subcategory":"[Аудио] Русская литература","torrentSize":"547 MB","torrentLink":"magnet:?xt=urn:btih:BE4CDB3BA4C4432818BC5B94176F8A6814CB022D&tr=http%3A%2F%2Fbt2.t-ru.org%2Fann%3Fmagnet","coverImageUrl":"http://www.ozon.ru/multimedia/books_covers/1000478966.jpg","URL":"https://rutracker.org/forum/viewtopic.php?t=1406873"}
{"name":"Пелевин Виктор – Непобедимое солнце [Пугач Алевтина, 2020, 64 kbps, MP3]","category":"Художественная литература","subcategory":"[Аудио] Русская литература","torrentSize":"452.3 MB","torrentLink":"magnet:?xt=urn:btih:E467641736A40AA78F3FB2D11417A5DDC43E6C1F&tr=http%3A%2F%2Fbt3.t-ru.org%2Fann%3Fmagnet","coverImageUrl":"https://i2.imageban.ru/out/2020/11/16/80e327e7702e984b694ca34aa34a4acd.jpg","URL":"https://rutracker.org/forum/viewtopic.php?t=5970113"}
{"name":"Липскеров Дмитрий - Туристический сбор в рай [Михаил Горевой, 2021, 128 kbps, MP3]","category":"Художественная литература","subcategory":"[Аудио] Русская литература","torrentSize":"547.6 MB","torrentLink":"magnet:?xt=urn:btih:AE943A510ADB486B66974356DD06882EBA214779&tr=http%3A%2F%2Fbt3.t-ru.org%2Fann%3Fmagnet","coverImageUrl":"https://i120.fastpic.org/big/2022/1009/58/2953f26d6eba8e9a7447c7370a1b8a58.jpg","URL":"https://rutracker.org/forum/viewtopic.php?t=6268174"}
{"name":"Черный Саша - У моря [Гуржий Юрий, (ЛИ), 2020, 256 kbps, MP3]","category":"Художественная литература","subcategory":"[Аудио] Русская литература","torrentSize":"14 MB","torrentLink":"magnet:?xt=urn:btih:FC7F02E67E196C96E6EFAFA9E616AC34233838A6&tr=http%3A%2F%2Fbt4.t-ru.org%2Fann%3Fmagnet","coverImageUrl":"https://i114.fastpic.ru/big/2020/1130/98/dc8bf0bd8f277dbecc50c69da618b698.jpg","URL":"https://rutracker.org/forum/viewtopic.php?t=5976983"}
{"name":"Довлатов Сергей - Иностранка [Ефим Шифрин, 2016, 320 kbps, MP3]","category":"Художественная литература","subcategory":"[Аудио] Русская литература","torrentSize":"440.9 MB","torrentLink":"magnet:?xt=urn:btih:B954315987C0FE9C712FECD6E41B7964C0820205&tr=http%3A%2F%2Fbt2.t-ru.org%2Fann%3Fmagnet","coverImageUrl":"http://i84.fastpic.ru/big/2016/1126/e2/435a633fe52e877c7f7e82f2cc9a2be2.jpg","URL":"https://rutracker.org/forum/viewtopic.php?t=5316652"}
{"name":"Толстой Лев - Не могу молчать. Статьи о войне, насилии, любви, безверии и непротивлении злу [Алексей Комиссаров, 2022, 80 kbps, MP3]","category":"Художественная литература","subcategory":"[Аудио] Русская литература","torrentSize":"268.8 MB","torrentLink":"magnet:?xt=urn:btih:D8408FBA5175D168EBD0F91D9EBBB25384A06938&tr=http%3A%2F%2Fbt2.t-ru.org%2Fann%3Fmagnet","coverImageUrl":"https://i120.fastpic.org/big/2022/0826/c8/4e1a5ab29de1c5db01d51a1a5d83adc8.jpg","URL":"https://rutracker.org/forum/viewtopic.php?t=6250902"}
{"name":"Колина Елена - Дневник новой русской [Ольга Белявская, 2006, 112 кбит/с]","category":"Художественная литература","subcategory":"[Аудио] Русская литература","torrentSize":"616.2 MB","torrentLink":"magnet:?xt=urn:btih:6275284C3C68079B889AE4F2A6499E8FF8452829&tr=http%3A%2F%2Fbt.t-ru.org%2Fann%3Fmagnet","coverImageUrl":"http://download.akniga.ru/Pics/P12_3205.jpg","URL":"https://rutracker.org/forum/viewtopic.php?t=504768"}
{"name":"Пелевин Виктор - Свет горизонта [Сергей Чонишвили, 2020, 144 kbps, MP3]","category":"Художественная литература","subcategory":"[Аудио] Русская литература","torrentSize":"57.1 MB","torrentLink":"magnet:?xt=urn:btih:0525A925F02C722A7A5E5CE11FC684E4346A8C80&tr=http%3A%2F%2Fbt2.t-ru.org%2Fann%3Fmagnet","coverImageUrl":"https://i116.fastpic.org/big/2022/0211/ec/bbe19c36a8fafdb20f5b778217349fec.jpg","URL":"https://rutracker.org/forum/viewtopic.php?t=6177278"}
{"name":"Сологуб Фёдор - Красногубая гостья [Яковлев Вадим, 2011 г., 128 kbps, MP3]","category":"Художественная литература","subcategory":"[Аудио] Русская литература","torrentSize":"77.1 MB","torrentLink":"magnet:?xt=urn:btih:32EBDAAB560959DD2971CD50B2DCFEE7A1D98B56&tr=http%3A%2F%2Fbt.t-ru.org%2Fann%3Fmagnet","coverImageUrl":"http://i61.fastpic.ru/big/2014/0610/67/1858618783256dba34d1b9c63ef04367.jpg","URL":"https://rutracker.org/forum/viewtopic.php?t=4758861"}
{"name":"Достоевский Федор Михайлович - Идиот [Владимир Еремин, 2014 г., 64 kbps, MP3]","category":"Художественная литература","subcategory":"[Аудио] Русская литература","torrentSize":"733.2 MB","torrentLink":"magnet:?xt=urn:btih:332F8502682A5CEA52F8F119CE41E868F3DA5349&tr=http%3A%2F%2Fbt3.t-ru.org%2Fann%3Fmagnet","coverImageUrl":"http://i65.fastpic.ru/big/2014/1012/a4/6c2a3957673661d16132ffb0d3a1c9a4.jpg","URL":"https://rutracker.org/forum/viewtopic.php?t=4844054"}
{"name":"Харуки Мураками - Дэнс, дэнс, дэнс [Князев Игорь, 2020, 128 kbps, MP3]","category":"Художественная литература","subcategory":"[Аудио] Зарубежная литература","torrentSize":"1.21 GB","torrentLink":"magnet:?xt=urn:btih:12034AC82D2B134BFACE7E61EAABDDB292542E49&tr=http%3A%2F%2Fbt2.t-ru.org%2Fann%3Fmagnet","coverImageUrl":"https://i5.imageban.ru/out/2022/05/11/1775b8b724a1f839fad54843a80dd1d5.jpg","URL":"https://rutracker.org/forum/viewtopic.php?t=6149034"}
{"name":"Хаксли Олдос - О дивный новый мир [Игорь Князев, 2020, 128 kbps, MP3]","category":"Художественная литература","subcategory":"[Аудио] Зарубежная литература","torrentSize":"460.5 MB","torrentLink":"magnet:?xt=urn:btih:7FBD3594418E299DC8B57333D5A0D8A650CDFCFC&tr=http%3A%2F%2Fbt4.t-ru.org%2Fann%3Fmagnet","coverImageUrl":"https://i116.fastpic.org/big/2021/1112/e7/13ce2b4439d55170533f56493b566de7.jpg","URL":"https://rutracker.org/forum/viewtopic.php?t=6135508"}
{"name":"Кафка Франц - Нора [ИГрин (ЛИ), 2022, 128 kbps, MP3]","category":"Художественная литература","subcategory":"[Аудио] Зарубежная литература","torrentSize":"98.5 MB","torrentLink":"magnet:?xt=urn:btih:1C18AB8259E5FA4AC8E3610407ED4089546A1950&tr=http%3A%2F%2Fbt2.t-ru.org%2Fann%3Fmagnet","coverImageUrl":"https://i116.fastpic.org/big/2022/0303/e6/3f0ac43289c961a02c16b437dd8233e6.jpg","URL":"https://rutracker.org/forum/viewtopic.php?t=6186462"}
{"name":"Герберт Фрэнк – Ловец душ [Олег Булдаков, 2021, 192 kbps, MP3]","category":"Художественная литература","subcategory":"[Аудио] Зарубежная литература","torrentSize":"706.7 MB","torrentLink":"magnet:?xt=urn:btih:864D68934F063FFF0B37E569BC71FEA61E9F3FA8&tr=http%3A%2F%2Fbt3.t-ru.org%2Fann%3Fmagnet","coverImageUrl":"https://i2.imageban.ru/out/2021/06/25/7f74b781d380bba0b8fd69496a1565ca.jpg","URL":"https://rutracker.org/forum/viewtopic.php?t=6072940"}
{"name":"Гашек Ярослав - Похождения бравого солдата Швейка [Владимир Самойлов, 2004 г., 128 kbps, MP3]","category":"Художественная литература","subcategory":"[Аудио] Зарубежная литература","torrentSize":"1.58 GB","torrentLink":"magnet:?xt=urn:btih:6C2CCEDA6F665F0C94896317BF1A83F32DA4CB84&tr=http%3A%2F%2Fbt2.t-ru.org%2Fann%3Fmagnet","coverImageUrl":"http://i63.fastpic.ru/big/2014/1114/38/a8843a537cf572074e004d1da435da38.jpg","URL":"https://rutracker.org/forum/viewtopic.php?t=4868558"}
{"name":"Метьюрин Чарлз - Мельмот Скиталец[Поздняков Михаил, 2015 г., 128 kbps, 44 kHz, Моно, MP3]","category":"Художественная литература","subcategory":"[Аудио] Зарубежная литература","torrentSize":"2.34 GB","torrentLink":"magnet:?xt=urn:btih:67328D41039D5B706D9A4B02118DA834B89CFC23&tr=http%3A%2F%2Fbt4.t-ru.org%2Fann%3Fmagnet","coverImageUrl":"http://s15.postimg.org/5jhrw0g3v/image.jpg","URL":"https://rutracker.org/forum/viewtopic.php?t=5032611"}
{"name":"Оруэлл Джордж - 1984 [Александр Клюквин, 2022, 128 kbps, MP3]","category":"Художественная литература","subcategory":"[Аудио] Зарубежная литература","torrentSize":"525 MB","torrentLink":"magnet:?xt=urn:btih:BC5D5A98853A5EA37C464FD9A8E8DF989E374635&tr=http%3A%2F%2Fbt3.t-ru.org%2Fann%3Fmagnet","coverImageUrl":"https://i120.fastpic.org/big/2022/0918/e7/e73af1f52de7db23d667459d14a801e7.jpg","URL":"https://rutracker.org/forum/viewtopic.php?t=6259840"}
{"name":"Вулф Вирджиния - Рассказы [Ведьма (ЛИ), 2013 г., 128 kbps, MP3]","category":"Художественная литература","subcategory":"[Аудио] Зарубежная литература","torrentSize":"297.7 MB","torrentLink":"magnet:?xt=urn:btih:3E0B53C71ECECACD440EAF2A5A15F58B51C510DF&tr=http%3A%2F%2Fbt4.t-ru.org%2Fann%3Fmagnet","coverImageUrl":"http://i60.fastpic.ru/big/2013/1226/28/afa6adec1709b7c26e94282af8029228.jpg","URL":"https://rutracker.org/forum/viewtopic.php?t=4625096"}
{"name":"Мартен дю Гар Роже. - Семья Тибо [Евгений Терновский, 2022, 96 kbps, MP3]","category":"Художественная литература","subcategory":"[Аудио] Зарубежная литература","torrentSize":"3.4 GB","torrentLink":"magnet:?xt=urn:btih:AC91388F07AEE5806CE30BB30D7A34D0D2DB868A&tr=http%3A%2F%2Fbt.t-ru.org%2Fann%3Fmagnet","coverImageUrl":"https://i120.fastpic.org/big/2022/1022/2a/56cfe69ebee3cfb22970455fdccb842a.jpg","URL":"https://rutracker.org/forum/viewtopic.php?t=6273926"}
{"name":"Манн Генрих - Счета жизни [Александр Бордуков, 2020, 96 kbps, MP3]","category":"Художественная литература","subcategory":"[Аудио] Зарубежная литература","torrentSize":"141.9 MB","torrentLink":"magnet:?xt=urn:btih:F83CAE4E2EA53E1BC30BEF07CBB331DE5E4589CE&tr=http%3A%2F%2Fbt3.t-ru.org%2Fann%3Fmagnet","coverImageUrl":"https://i120.fastpic.org/big/2022/1020/16/c9c0cd6592dc8f981941d5c70fdd7116.jpg","URL":"https://rutracker.org/forum/viewtopic.php?t=6272851"}
{"name":"Робсон Дженнифер - Платье королевы [Любовь Толкалина, 2021, 128 kbps, MP3]","category":"Художественная литература","subcategory":"[Аудио] Зарубежная литература","torrentSize":"550.2 MB","torrentLink":"magnet:?xt=urn:btih:A7246558DE0A5BA38A498098C05C19CD89E7E35C&tr=http%3A%2F%2Fbt.t-ru.org%2Fann%3Fmagnet","coverImageUrl":"https://a.radikal.ru/a30/2104/af/322db6abd9fc.jpg","URL":"https://rutracker.org/forum/viewtopic.php?t=6042655"}
{"name":"Пшавела Важа - Свадьба соек + лекция Дмитрия Быкова [Дмитрий Быков, 2021, 96 kbps, MP3]","category":"Художественная литература","subcategory":"[Аудио] Зарубежная литература","torrentSize":"111 MB","torrentLink":"magnet:?xt=urn:btih:D482E1285995A7726B3F4A87D7E526DD463B7190&tr=http%3A%2F%2Fbt3.t-ru.org%2Fann%3Fmagnet","coverImageUrl":"https://i120.fastpic.org/big/2022/1022/47/0d359dfa61a9476bbc2dff6d4065df47.jpg","URL":"https://rutracker.org/forum/viewtopic.php?t=6273844"}
{"name":"Флобер Гюстав - Воспитание чувств (Сентиментальное воспитание) [Максим Суслов, 2017, 96 kbps, MP3]","category":"Художественная литература","subcategory":"[Аудио] Зарубежная литература","torrentSize":"724.2 MB","torrentLink":"magnet:?xt=urn:btih:63E7D67C3EDC6283FC5D9DDE79EAFFC139FB61A1&tr=http%3A%2F%2Fbt.t-ru.org%2Fann%3Fmagnet","coverImageUrl":"https://i120.fastpic.org/big/2022/1022/03/fe42252f8eb5833a8772a6bfb74f0f03.jpg","URL":"https://rutracker.org/forum/viewtopic.php?t=6273842"}
{"name":"Кобо Абэ - \"Женщина в песках\" [А. Зарецкий, С. Старчиков, Е. Морозова, А. Хорлин, Е. Терновский, CBR 192]","category":"Художественная литература","subcategory":"[Аудио] Зарубежная литература","torrentSize":"582.7 MB","torrentLink":"magnet:?xt=urn:btih:5AFF69AF77E480F5AFF7CE7F9170DBC7D5EC8BBA&tr=http%3A%2F%2Fbt.t-ru.org%2Fann%3Fmagnet","URL":"https://rutracker.org/forum/viewtopic.php?t=137848"}
{"name":"Мориак Франсуа - Фарисейка [Дмитрий Оргин, 2022, 128 kbps, MP3]","category":"Художественная литература","subcategory":"[Аудио] Зарубежная литература","torrentSize":"493.4 MB","torrentLink":"magnet:?xt=urn:btih:B5C12996A73E8403875C0A2DC4E0819F2D971847&tr=http%3A%2F%2Fbt.t-ru.org%2Fann%3Fmagnet","coverImageUrl":"https://i120.fastpic.org/big/2022/1021/29/c15eaeb1a79405153405360acd16ae29.jpg","URL":"https://rutracker.org/forum/viewtopic.php?t=6273334"}
{"name":"Даррелл Джеральд - Мама на выданье [Ерисанова Ирина, 2011, 96 kbps, MP3]","category":"Художественная литература","subcategory":"[Аудио] Зарубежная литература","torrentSize":"301.8 MB","torrentLink":"magnet:?xt=urn:btih:BD7406152B7A71D93195EB3093BB3642FFF1EE7B&tr=http%3A%2F%2Fbt3.t-ru.org%2Fann%3Fmagnet","coverImageUrl":"http://s017.radikal.ru/i419/1111/d2/e45e52278cda.jpg","URL":"https://rutracker.org/forum/viewtopic.php?t=3808177"}
{"name":"Уорф Дженнифер - Вызовите акушерку 03, Прощание с Ист-Эндом [Наталия Казначеева, 2022, 128 kbps, MP3]","category":"Художественная литература","subcategory":"[Аудио] Зарубежная литература","torrentSize":"590.5 MB","torrentLink":"magnet:?xt=urn:btih:294CB0A4113B57DF01CFCBD3D1EAB22124B21520&tr=http%3A%2F%2Fbt4.t-ru.org%2Fann%3Fmagnet","coverImageUrl":"https://i120.fastpic.org/big/2022/1021/9d/2f4bdbb4ec8de2f2774af77c37849c9d.jpg","URL":"https://rutracker.org/forum/viewtopic.php?t=6273335"}
{"name":"Саид Курбан - Али и Нино [Юлия Тархова, 2022, 64 kbps, MP3]","category":"Художественная литература","subcategory":"[Аудио] Зарубежная литература","torrentSize":"274.6 MB","torrentLink":"magnet:?xt=urn:btih:3304905F7F0DBED8B667C27F17731E2964571535&tr=http%3A%2F%2Fbt4.t-ru.org%2Fann%3Fmagnet","coverImageUrl":"https://i120.fastpic.org/big/2022/0612/7b/daf93b621cec01ecf01a5199e901ad7b.jpg","URL":"https://rutracker.org/forum/viewtopic.php?t=6225145"}
{"name":"Генри О - Плюшевый Котенок [Иван Литвинов, 2013, 56 kbps, MP3]","category":"Художественная литература","subcategory":"[Аудио] Зарубежная литература","torrentSize":"6.8 MB","torrentLink":"magnet:?xt=urn:btih:CC5017CE9C8AD7F48B3DB653D12235D90D938A32&tr=http%3A%2F%2Fbt2.t-ru.org%2Fann%3Fmagnet","coverImageUrl":"http://i100.fastpic.ru/big/2018/0826/82/084e8e6f2b2ee7479031786cd0592e82.jpg","URL":"https://rutracker.org/forum/viewtopic.php?t=5605430"}
{"name":"Диас Джуно - Короткая фантастическая жизнь Оскара Вау [Кирилл Радциг, Анастасия Шумилкина, 2022, 128 kbps, MP3]","category":"Художественная литература","subcategory":"[Аудио] Зарубежная литература","torrentSize":"627.3 MB","torrentLink":"magnet:?xt=urn:btih:906C5A63F3E18262A1A0432B7CE69F0CFB5B912E&tr=http%3A%2F%2Fbt4.t-ru.org%2Fann%3Fmagnet","coverImageUrl":"https://i120.fastpic.org/big/2022/1011/bb/67c77a44ac9066d70dc2260e2766acbb.jpg","URL":"https://rutracker.org/forum/viewtopic.php?t=6268917"}
{"name":"Милорад Павич - Последняя любовь в Константинополе [Сергей Чонишвили, 2006, 320 кбит/с]","category":"Художественная литература","subcategory":"[Аудио] Зарубежная литература","torrentSize":"585.9 MB","torrentLink":"magnet:?xt=urn:btih:B5C7DD44EB7755F6FCA1BAAFF8759B6E4326B6BF&tr=http%3A%2F%2Fbt.t-ru.org%2Fann%3Fmagnet","coverImageUrl":"http://www.moymir.ru/PRODUCT/IMAGES/i41/B/00000005934749_267_1.jpg","URL":"https://rutracker.org/forum/viewtopic.php?t=738335"}
{"name":"Кох Герман - Ужин [Иван Литвинов, 2016, 128 kbps, MP3]","category":"Художественная литература","subcategory":"[Аудио] Зарубежная литература","torrentSize":"429.9 MB","torrentLink":"magnet:?xt=urn:btih:3482FCE88CE0BB70D936C7BF96ED60A6AA5A0001&tr=http%3A%2F%2Fbt.t-ru.org%2Fann%3Fmagnet","coverImageUrl":"http://s017.radikal.ru/i443/1610/b5/a47830d9a7cd.jpg","URL":"https://rutracker.org/forum/viewtopic.php?t=5298556"}
{"name":"Янагихара Ханья - Маленькая жизнь [Леонов Андрей, 2020, 96 kbps, MP3]","category":"Художественная литература","subcategory":"[Аудио] Зарубежная литература","torrentSize":"1.29 GB","torrentLink":"magnet:?xt=urn:btih:758E305F9DE0D6E9B1F1989129E81548756A46AF&tr=http%3A%2F%2Fbt.t-ru.org%2Fann%3Fmagnet","coverImageUrl":"https://i.ibb.co/1MFS45s/Yanagihara-H-Malenkaya-zhizn-Leonov-A.jpg","URL":"https://rutracker.org/forum/viewtopic.php?t=5929063"}
{"name":"Исигуро Кадзуо - Остаток дня [Игорь Князев, 2018, 96 kbps, MP3]","category":"Художественная литература","subcategory":"[Аудио] Зарубежная литература","torrentSize":"363.5 MB","torrentLink":"magnet:?xt=urn:btih:3C3B1746D72010FD4FD17332C516E3078455E96C&tr=http%3A%2F%2Fbt.t-ru.org%2Fann%3Fmagnet","coverImageUrl":"http://i105.fastpic.ru/big/2018/0713/6e/1f678319e2cebb3b2f5ac4cef837896e.jpg","URL":"https://rutracker.org/forum/viewtopic.php?t=5586705"}
{"name":"Оруэлл Джордж - 1984 [Сергей Чонишвили, 2021, 128 kbps, MP3]","category":"Художественная литература","subcategory":"[Аудио] Зарубежная литература","torrentSize":"539.1 MB","torrentLink":"magnet:?xt=urn:btih:B0EA34708B92F82C16F2C271F8AF4959D0CE8FCC&tr=http%3A%2F%2Fbt3.t-ru.org%2Fann%3Fmagnet","coverImageUrl":"https://i114.fastpic.ru/big/2021/0201/db/c3f50c5f53c58f3df53bbcc40d9f83db.jpg","URL":"https://rutracker.org/forum/viewtopic.php?t=6005109"}
{"name":"Оруэлл Джордж - 1984 [Владимир Левашев, 2022, 112 kbps, MP3]","category":"Художественная литература","subcategory":"[Аудио] Зарубежная литература","torrentSize":"692.7 MB","torrentLink":"magnet:?xt=urn:btih:D118FDD79C26EB1ABEB8CA7AE64B19E5EB3590A2&tr=http%3A%2F%2Fbt4.t-ru.org%2Fann%3Fmagnet","coverImageUrl":"https://i120.fastpic.org/big/2022/0906/6b/1e1363b12ce70305ee81d0877efb8f6b.jpg","URL":"https://rutracker.org/forum/viewtopic.php?t=6255530"}
{"name":"Бронте Эмили - Грозовой перевал [Григорий Перель, Наталья Казначеева, 2020, 128 kbps, MP3]","category":"Художественная литература","subcategory":"[Аудио] Зарубежная литература","torrentSize":"821.9 MB","torrentLink":"magnet:?xt=urn:btih:A9233A9CEB742D980F2C5F51876CCD82318E200D&tr=http%3A%2F%2Fbt2.t-ru.org%2Fann%3Fmagnet","coverImageUrl":"http://images.vfl.ru/ii/1601103953/3c9fcf41/31747518.jpg","URL":"https://rutracker.org/forum/viewtopic.php?t=5946797"}
{"name":"Бронте Эмили - Грозовой перевал [Вячеслав Манылов, 2019, 128 kbps, MP3]","category":"Художественная литература","subcategory":"[Аудио] Зарубежная литература","torrentSize":"1.07 GB","torrentLink":"magnet:?xt=urn:btih:93428F55FB4C676E4672DAEA9F48E21A62B6531A&tr=http%3A%2F%2Fbt3.t-ru.org%2Fann%3Fmagnet","coverImageUrl":"https://i120.fastpic.org/big/2022/0726/bb/4f6bfdfe8acfc0fa0ee5c840a1ce35bb.png","URL":"https://rutracker.org/forum/viewtopic.php?t=6239651"}
{"name":"Мюссо Гийом - Прошло семь лет… [Суслов Максим, 2019, 128 kbps, MP3]","category":"Художественная литература","subcategory":"[Аудио] Зарубежная литература","torrentSize":"491.9 MB","torrentLink":"magnet:?xt=urn:btih:6170F936C93F541D8C04A200B3D4EDAE91FB91A0&tr=http%3A%2F%2Fbt.t-ru.org%2Fann%3Fmagnet","coverImageUrl":"https://i115.fastpic.ru/big/2021/0705/b0/be26c14852a6b9542d15e0592176ceb0.jpg","URL":"https://rutracker.org/forum/viewtopic.php?t=6077448"}
{"name":"Мюссо Гийом - Сентрал-парк [Петрова Ольга, 2019, 96 kbps, MP3]","category":"Художественная литература","subcategory":"[Аудио] Зарубежная литература","torrentSize":"377 MB","torrentLink":"magnet:?xt=urn:btih:A4A474B2E4DF4010B0F9BCD76E3DFA9EDDE25515&tr=http%3A%2F%2Fbt.t-ru.org%2Fann%3Fmagnet","coverImageUrl":"https://b.radikal.ru/b34/1908/ac/b6c5cc11c723.jpg","URL":"https://rutracker.org/forum/viewtopic.php?t=5767423"}
{"name":"Урреа Луис Альберто - Дом падших ангелов [Алексей Багдасаров, 2020, 128 kbps, MP3]","category":"Художественная литература","subcategory":"[Аудио] Зарубежная литература","torrentSize":"632.1 MB","torrentLink":"magnet:?xt=urn:btih:3B3340306ED5EB63771EAA2A58BD57DF183EFD4A&tr=http%3A%2F%2Fbt2.t-ru.org%2Fann%3Fmagnet","coverImageUrl":"https://i111.fastpic.ru/big/2020/0409/c1/c39326441befb0ad55ef77ff1d5260c1.jpg","URL":"https://rutracker.org/forum/viewtopic.php?t=5878232"}
{"name":"Мюссо Гийом - Бумажная девушка [Броцкая Леонтина, 2014 г., 96 kbps, MP3]","category":"Художественная литература","subcategory":"[Аудио] Зарубежная литература","torrentSize":"501.6 MB","torrentLink":"magnet:?xt=urn:btih:65A674767B20C8329C87EA4A24500469391D99C6&tr=http%3A%2F%2Fbt3.t-ru.org%2Fann%3Fmagnet","coverImageUrl":"http://i65.fastpic.ru/big/2014/0712/76/c8af077a70b9f7d666c95fda2b4afc76.jpg","URL":"https://rutracker.org/forum/viewtopic.php?t=4781517"}
{"name":"Мердок Айрис - Отрубленная голова / Отсеченная голова [Николай Савицкий, 2013 г., 96 кбит/с, MP3]","category":"Художественная литература","subcategory":"[Аудио] Зарубежная литература","torrentSize":"447.5 MB","torrentLink":"magnet:?xt=urn:btih:DCDBA4732F3194DF65AD817844DEFD33DF1E1418&tr=http%3A%2F%2Fbt4.t-ru.org%2Fann%3Fmagnet","coverImageUrl":"https://a.radikal.ru/a10/2111/f7/e1d4a87ad7b3.jpg","URL":"https://rutracker.org/forum/viewtopic.php?t=4346416"}
{"name":"Эко Умберто - Имя розы [Михаил Ткаченко (ЛИ), 2022, 320 kbps, MP3]","category":"Художественная литература","subcategory":"[Аудио] Зарубежная литература","torrentSize":"366.2 MB","torrentLink":"magnet:?xt=urn:btih:0FC65B114CC4D50952C9729BC19AF23A51EA4264&tr=http%3A%2F%2Fbt3.t-ru.org%2Fann%3Fmagnet","coverImageUrl":"https://i120.fastpic.org/big/2022/0815/09/dea86a376270259eb1cb3095798c4e09.jpg","URL":"https://rutracker.org/forum/viewtopic.php?t=6246862"}
{"name":"Мердок Айрис - Под сетью [Репина Светлана, 2011 г., 96 kbps, MP3]","category":"Художественная литература","subcategory":"[Аудио] Зарубежная литература","torrentSize":"437.7 MB","torrentLink":"magnet:?xt=urn:btih:65A084808DE52933F42319E18843198A01B64EC3&tr=http%3A%2F%2Fbt.t-ru.org%2Fann%3Fmagnet","coverImageUrl":"http://i015.radikal.ru/1105/39/5d1c6a82cc9c.jpg","URL":"https://rutracker.org/forum/viewtopic.php?t=3572406"}
{"name":"Гюго Виктор - Человек, который смеется [Алексей Борзунов, 2013 г., 128 kbps, MP3]","category":"Художественная литература","subcategory":"[Аудио] Зарубежная литература","torrentSize":"1.21 GB","torrentLink":"magnet:?xt=urn:btih:55AFFB80B009EF292E6F467F902E758CB03E0C74&tr=http%3A%2F%2Fbt2.t-ru.org%2Fann%3Fmagnet","coverImageUrl":"http://i50.fastpic.ru/big/2013/0730/26/9f1fff616b0c4b055d8e0abb1b201b26.jpg","URL":"https://rutracker.org/forum/viewtopic.php?t=4499719"}
{"name":"Габриэль Витткоп - Некрофил [Михаил Прокопов, (ЛИ), 2016 г., 192 kbps, MP3]","category":"Художественная литература","subcategory":"[Аудио] Зарубежная литература","torrentSize":"166.6 MB","torrentLink":"magnet:?xt=urn:btih:0944F69C8821701D198B80A714C349B055A51B26&tr=http%3A%2F%2Fbt2.t-ru.org%2Fann%3Fmagnet","coverImageUrl":"https://pp.vk.me/c637525/v637525687/fb3b/SSSVBQ4Wrvc.jpg","URL":"https://rutracker.org/forum/viewtopic.php?t=5289712"}
{"name":"Фицджеральд Фрэнсис Скотт - Великий Гэтсби [Михаил Тихонов, 2021, 56 kbps, MP3]","category":"Художественная литература","subcategory":"[Аудио] Зарубежная литература","torrentSize":"143.3 MB","torrentLink":"magnet:?xt=urn:btih:B0478DE3EF963576FB72A67C52136D022E121A81&tr=http%3A%2F%2Fbt.t-ru.org%2Fann%3Fmagnet","coverImageUrl":"https://i114.fastpic.ru/big/2021/0120/62/0ca36e66d7628b4257403f18ce6a9c62.jpg","URL":"https://rutracker.org/forum/viewtopic.php?t=5999391"}
{"name":"Цвейг Стефан - Страх [Михаил Прокопов (ЛИ), 2015 г., 192 kbps, MP3]","category":"Художественная литература","subcategory":"[Аудио] Зарубежная литература","torrentSize":"152.9 MB","torrentLink":"magnet:?xt=urn:btih:EA7A8DA3623963499DA12C2062D7D64065DB1723&tr=http%3A%2F%2Fbt.t-ru.org%2Fann%3Fmagnet","coverImageUrl":"http://cs627817.vk.me/v627817687/23e8a/N4QT4oUVfM8.jpg","URL":"https://rutracker.org/forum/viewtopic.php?t=5124141"}
{"name":"Гувер Колин, Фишер Таррин - Никогда Никогда (В любви можно все) [Александр Зачиняев, Елена Греб, 2018, 128 kbps, MP3]","category":"Художественная литература","subcategory":"[Аудио] Зарубежная литература","torrentSize":"225.8 MB","torrentLink":"magnet:?xt=urn:btih:31E96075AC655D76A81C640C91565A9E9D47E4BA&tr=http%3A%2F%2Fbt3.t-ru.org%2Fann%3Fmagnet","coverImageUrl":"http://i103.fastpic.ru/big/2018/0917/02/d5ab160e037117732f8985bc4cd73502.jpg","URL":"https://rutracker.org/forum/viewtopic.php?t=5614883"}
{"name":"Гувер Колин; Фишер Таррин – Никогда Никогда 2, Не прекращай любить [Зачиняев Александр; Греб Елена, 2018, 56 kbps, MP3]","category":"Художественная литература","subcategory":"[Аудио] Зарубежная литература","torrentSize":"59 MB","torrentLink":"magnet:?xt=urn:btih:E10EE8809000C505F2EE5976BC79A08539378D21&tr=http%3A%2F%2Fbt.t-ru.org%2Fann%3Fmagnet","coverImageUrl":"https://i3.imageban.ru/out/2020/07/01/b5570eb3702e35e1ea8c2645968eee1f.jpg","URL":"https://rutracker.org/forum/viewtopic.php?t=5914421"}
{"name":"Дойль Артур Конан - Письма Старка Монро [Петр Таганов, 2012 г., 192 kbps, MP3]","category":"Художественная литература","subcategory":"[Аудио] Зарубежная литература","torrentSize":"348.4 MB","torrentLink":"magnet:?xt=urn:btih:E1977CF5CF2DCF5B722B8EE17776C77BF5F5A4BA&tr=http%3A%2F%2Fbt3.t-ru.org%2Fann%3Fmagnet","coverImageUrl":"http://i41.fastpic.ru/big/2012/0829/26/1194fe034b80f774a3046e0cb0781626.jpg","URL":"https://rutracker.org/forum/viewtopic.php?t=4168018"}
{"name":"Брэдбери Рэй - Вино из одуванчиков [Михаил Прокопов, 2019, 128 kbps, MP3]","category":"Художественная литература","subcategory":"[Аудио] Зарубежная литература","torrentSize":"487.2 MB","torrentLink":"magnet:?xt=urn:btih:D25E6C5B413B0C83A2FE67E545F65D53E7C83B19&tr=http%3A%2F%2Fbt.t-ru.org%2Fann%3Fmagnet","coverImageUrl":"https://i3.imageban.ru/out/2019/10/14/634606df997df84dcce91a96c7201f2d.jpg","URL":"https://rutracker.org/forum/viewtopic.php?t=5791375"}
{"name":"Дойль Артур Конан - Трагедия пассажиров \"Короско\" [Бабич Ольга, 2013 г., 96 kbps, MP3]","category":"Художественная литература","subcategory":"[Аудио] Зарубежная литература","torrentSize":"456.4 MB","torrentLink":"magnet:?xt=urn:btih:3CC53635FA6617046F5EABF60D1B3D75A1E4A60E&tr=http%3A%2F%2Fbt4.t-ru.org%2Fann%3Fmagnet","coverImageUrl":"http://i46.fastpic.ru/big/2013/0617/c4/359e38b447a97b288e14baf1063cd1c4.jpg","URL":"https://rutracker.org/forum/viewtopic.php?t=4467825"}
{"name":"Дойль Артур Конан - Рассказы (Капитан Шарки. Морские рассказы) [Владимир Левашёв, 2009, 192 kbps]","category":"Художественная литература","subcategory":"[Аудио] Зарубежная литература","torrentSize":"544.3 MB","torrentLink":"magnet:?xt=urn:btih:F794C166E8553FD6005E4F07D8324C66AC0E46D8&tr=http%3A%2F%2Fbt3.t-ru.org%2Fann%3Fmagnet","coverImageUrl":"http://i082.radikal.ru/0907/03/c4de507d030c.jpg","URL":"https://rutracker.org/forum/viewtopic.php?t=2025592"}
{"name":"Дойль Артур Конан - Страна туманов [Комиссар (ЛИ), 2013 г., 256 kbps, MP3]","category":"Художественная литература","subcategory":"[Аудио] Зарубежная литература","torrentSize":"1.15 GB","torrentLink":"magnet:?xt=urn:btih:909C96272C7830D1C36EFAD4D4D662F45BBAEBFF&tr=http%3A%2F%2Fbt3.t-ru.org%2Fann%3Fmagnet","coverImageUrl":"http://i57.fastpic.ru/big/2013/0906/cd/58376664ec7ed8a966ee3a31fb60d6cd.jpg","URL":"https://rutracker.org/forum/viewtopic.php?t=4528606"}
{"name":"Лион Фейхтвангер - Черт во Франции [Вячеслав Герасимов, 112 кбит/с]","category":"Художественная литература","subcategory":"[Аудио] Зарубежная литература","torrentSize":"173.2 MB","torrentLink":"magnet:?xt=urn:btih:1527E07C550C80C86735F69254C6534F3104154C&tr=http%3A%2F%2Fbt.t-ru.org%2Fann%3Fmagnet","coverImageUrl":"http://savepic.ru/170102.jpg","URL":"https://rutracker.org/forum/viewtopic.php?t=771801"}
{"name":"Хорхе Ф.И. Луис Борхес Асеведо - Проза разных лет [В.Герасимов, 128 кбит/с]","category":"Художественная литература","subcategory":"[Аудио] Зарубежная литература","torrentSize":"976.4 MB","torrentLink":"magnet:?xt=urn:btih:33A0E5DAFAA8E3CDB5D52F68B72859301410B044&tr=http%3A%2F%2Fbt.t-ru.org%2Fann%3Fmagnet","coverImageUrl":"http://i017.radikal.ru/0901/77/ab1b1e50e822.jpg","URL":"https://rutracker.org/forum/viewtopic.php?t=825778"}
{"name":"Эксбрайя Шарль - Ромео Тарчинини 3, Кьянти и кока-кола [Ирина Власова, (ЛИ), 2017, 128 kbps, MP3]","category":"Художественная литература","subcategory":"[Аудио] Зарубежная литература","torrentSize":"277.3 MB","torrentLink":"magnet:?xt=urn:btih:DDAAA0DFAEC4E91DF55057E24D22A66D902ECB6B&tr=http%3A%2F%2Fbt4.t-ru.org%2Fann%3Fmagnet","coverImageUrl":"http://i94.fastpic.ru/big/2017/0601/87/66630d839fc09f3c3f87b88cecbc1887.jpg","URL":"https://rutracker.org/forum/viewtopic.php?t=5410706"}
{"name":"Борхес Хорхе Луис - Проза разных лет [Герасимов Вячеслав, 2011, 96 kbps, MP3]","category":"Художественная литература","subcategory":"[Аудио] Зарубежная литература","torrentSize":"748.3 MB","torrentLink":"magnet:?xt=urn:btih:2B4D055A750FF087627FAF94B6D696BA98E39975&tr=http%3A%2F%2Fbt2.t-ru.org%2Fann%3Fmagnet","coverImageUrl":"http://s011.radikal.ru/i316/1110/84/596b2d9cdb48.jpg","URL":"https://rutracker.org/forum/viewtopic.php?t=3760063"}
{"name":"Вилла для общения раздела Современные любовные романы","category":"Художественная литература","subcategory":"[Аудио] Современные любовные романы","coverImageUrl":"http://parijanka.info/gallery/pics/smiles/podmig/podmig3.gif","URL":"https://rutracker.org/forum/viewtopic.php?t=6208182"}
{"name":"Колган Дженни Т. - Берег счастливых встреч [Алла Човжик, 2021, 128 kbps, MP3]","category":"Художественная литература","subcategory":"[Аудио] Современные любовные романы","torrentSize":"557.3 MB","torrentLink":"magnet:?xt=urn:btih:59EF8009D16B1B95D9BA2DE0E97C2D0D1F270706&tr=http%3A%2F%2Fbt2.t-ru.org%2Fann%3Fmagnet","coverImageUrl":"https://c.radikal.ru/c30/2105/ed/e5b2661675ae.jpg","URL":"https://rutracker.org/forum/viewtopic.php?t=6056983"}
{"name":"Сакру Ана - Рамиль [Аня Грэй, 2021, 56 kbps, MP3]","category":"Художественная литература","subcategory":"[Аудио] Современные любовные романы","torrentSize":"210.5 MB","torrentLink":"magnet:?xt=urn:btih:2F979441B5549829980FCF549E1EBF3B30190614&tr=http%3A%2F%2Fbt2.t-ru.org%2Fann%3Fmagnet","coverImageUrl":"https://i120.fastpic.org/big/2022/0712/41/f7212a088ee89ed6f5470f0233ac1541.jpg","URL":"https://rutracker.org/forum/viewtopic.php?t=6234947"}
{"name":"Ручей Наталья – Закрытое небо [Князева Ольга, 2019, 128 kbps, MP3]","category":"Художественная литература","subcategory":"[Аудио] Современные любовные романы","torrentSize":"232 MB","torrentLink":"magnet:?xt=urn:btih:5D2E483C2EB7087848267E1F46CF6E62DDB14EAE&tr=http%3A%2F%2Fbt3.t-ru.org%2Fann%3Fmagnet","coverImageUrl":"https://i1.imageban.ru/out/2020/01/16/df26a446ae6c28cd376e9de26895b712.jpg","URL":"https://rutracker.org/forum/viewtopic.php?t=5836364"}
{"name":"Кистяева Марина - Парни при погонах 1, Сердце офицера [Дмитрий Кузнецов, 2022, 128 kbps, MP3]","category":"Художественная литература","subcategory":"[Аудио] Современные любовные романы","torrentSize":"444 MB","torrentLink":"magnet:?xt=urn:btih:76700E16C80415358477BB265504993D8416D966&tr=http%3A%2F%2Fbt4.t-ru.org%2Fann%3Fmagnet","coverImageUrl":"https://i120.fastpic.org/big/2022/1002/83/70ff832404878394d1d3eea202149f83.jpg","URL":"https://rutracker.org/forum/viewtopic.php?t=6265291"}
{"name":"Гринвэлл Ольга - Снова с нами 5, Гречишный мёд [Василий Сёмин, 2021, 128 kbps, MP3]","category":"Художественная литература","subcategory":"[Аудио] Современные любовные романы","torrentSize":"833.9 MB","torrentLink":"magnet:?xt=urn:btih:D46D4F5116C5CE20C1F6511BBE907918DABA7DE4&tr=http%3A%2F%2Fbt4.t-ru.org%2Fann%3Fmagnet","coverImageUrl":"https://i120.fastpic.org/big/2022/0921/23/e442297c5374f86bad3d1d5005a07123.jpg","URL":"https://rutracker.org/forum/viewtopic.php?t=6261300"}
{"name":"Сэмпсон Фрейя - Библиотека моего сердца [Любовь Конева, 2022, 128 kbps, MP3]","category":"Художественная литература","subcategory":"[Аудио] Современные любовные романы","torrentSize":"441.8 MB","torrentLink":"magnet:?xt=urn:btih:CF94A12462A73CADA96889FD04B5522B736FB82C&tr=http%3A%2F%2Fbt3.t-ru.org%2Fann%3Fmagnet","coverImageUrl":"https://i120.fastpic.org/big/2022/0702/82/25526f558b17f46e6ac25d2006fa4882.jpg","URL":"https://rutracker.org/forum/viewtopic.php?t=6231892"}
{"name":"Кальби Иман - Она моя 4, Она моя 2... Бонус [Аня Грэй, 2021, 128 kbps, MP3]","category":"Художественная литература","subcategory":"[Аудио] Современные любовные романы","torrentSize":"66.1 MB","torrentLink":"magnet:?xt=urn:btih:D97B1F433ED55CECA83B175EE11B735EEF068BC6&tr=http%3A%2F%2Fbt3.t-ru.org%2Fann%3Fmagnet","coverImageUrl":"https://i116.fastpic.org/big/2021/1126/89/aa7ed3ed23ee1ffee345dba56bcdae89.jpg","URL":"https://rutracker.org/forum/viewtopic.php?t=6142211"}
{"name":"Кальби Иман - Она моя 2, Не твоя… Книга вторая [Аня Грэй, 2021, 128 kbps, MP3]","category":"Художественная литература","subcategory":"[Аудио] Современные любовные романы","torrentSize":"455.9 MB","torrentLink":"magnet:?xt=urn:btih:94CC08F7E572B87051B31B6ED3E60DDD1357EE41&tr=http%3A%2F%2Fbt2.t-ru.org%2Fann%3Fmagnet","coverImageUrl":"https://i116.fastpic.org/big/2021/1126/41/87496aa5673643dc01346e912d0a2641.jpg","URL":"https://rutracker.org/forum/viewtopic.php?t=6142195"}
{"name":"Кальби Иман - Она моя 3, Ничья… Книга третья [Аня Грэй, 2021, 128 kbps, MP3]","category":"Художественная литература","subcategory":"[Аудио] Современные любовные романы","torrentSize":"665 MB","torrentLink":"magnet:?xt=urn:btih:C86E1494580816CAF02D127A61C89700B51DF836&tr=http%3A%2F%2Fbt3.t-ru.org%2Fann%3Fmagnet","coverImageUrl":"https://i116.fastpic.org/big/2021/1126/4d/1a5f888538a0cde608fe14b8f371b44d.jpg","URL":"https://rutracker.org/forum/viewtopic.php?t=6142204"}
{"name":"Солдатова Татьяна - Любовь на десерт [Евгения Ваган, Илья Сланевский, 2021, 128 kbps, MP3]","category":"Художественная литература","subcategory":"[Аудио] Современные любовные романы","torrentSize":"543.7 MB","torrentLink":"magnet:?xt=urn:btih:2EEF6557867699F1B658C04304FA5751F9838649&tr=http%3A%2F%2Fbt3.t-ru.org%2Fann%3Fmagnet","coverImageUrl":"https://i120.fastpic.org/big/2022/0918/7a/8d204fa4b79593483323256eec441a7a.jpg","URL":"https://rutracker.org/forum/viewtopic.php?t=6260110"}
{"name":"Гувер Колин - Тайный дневник Верити [Елена Греб, 2021, 56 kbps, MP3]","category":"Художественная литература","subcategory":"[Аудио] Современные любовные романы","torrentSize":"179.2 MB","torrentLink":"magnet:?xt=urn:btih:DAD7BF3999CB2D09D00C3BB6C69931435EAD8516&tr=http%3A%2F%2Fbt3.t-ru.org%2Fann%3Fmagnet","coverImageUrl":"https://c.radikal.ru/c29/2103/e2/73c38a485eb4.jpg","URL":"https://rutracker.org/forum/viewtopic.php?t=6022486"}
{"name":"Китагава Ясуси - Благодаря встрече с тобой [Шаронов Александр, 2021, 128 kbps, MP3]","category":"Художественная литература","subcategory":"[Аудио] Современные любовные романы","torrentSize":"98.9 MB","torrentLink":"magnet:?xt=urn:btih:B9D105390D6406838838BAC6450868912F2D9982&tr=http%3A%2F%2Fbt3.t-ru.org%2Fann%3Fmagnet","coverImageUrl":"https://i115.fastpic.ru/big/2021/0713/0a/17c51e61711d3dd811c7466f0f89490a.jpg","URL":"https://rutracker.org/forum/viewtopic.php?t=6080705"}
{"name":"Набокова Юлия - Маленький отель на Санторини [Екатерина Мухина, 2022, 128 kbps, MP3]","category":"Художественная литература","subcategory":"[Аудио] Современные любовные романы","torrentSize":"639.9 MB","torrentLink":"magnet:?xt=urn:btih:BA33D23C6035B54A639530E863D32264D75B59C6&tr=http%3A%2F%2Fbt3.t-ru.org%2Fann%3Fmagnet","coverImageUrl":"https://i120.fastpic.org/big/2022/0912/a0/424d738168aa55420984e69a634806a0.jpg","URL":"https://rutracker.org/forum/viewtopic.php?t=6257824"}
{"name":"Рымарь Диана - Ночной кошмар Купидона [Саша Брежнева, 2021, 128 kbps, MP3]","category":"Художественная литература","subcategory":"[Аудио] Современные любовные романы","torrentSize":"254.2 MB","torrentLink":"magnet:?xt=urn:btih:693186ADA0DDE03CCB1D7EBD5CCC266B745CD2AA&tr=http%3A%2F%2Fbt4.t-ru.org%2Fann%3Fmagnet","coverImageUrl":"https://c.radikal.ru/c15/2105/52/fc89d4754263.jpg","URL":"https://rutracker.org/forum/viewtopic.php?t=6060118"}
{"name":"Алюшина Татьяна - Девочка моя, или Одна кровь на двоих [Ольга Макарова, 2022, 128 kbps, MP3]","category":"Художественная литература","subcategory":"[Аудио] Современные любовные романы","torrentSize":"414.6 MB","torrentLink":"magnet:?xt=urn:btih:19A08B5AFE68F9A9A0EEEAF072B74383336D08DB&tr=http%3A%2F%2Fbt2.t-ru.org%2Fann%3Fmagnet","coverImageUrl":"https://i120.fastpic.org/big/2022/0626/3d/8ca5d989f7982b2dcae0ea14d2461a3d.jpg","URL":"https://rutracker.org/forum/viewtopic.php?t=6229938"}
{"name":"Кистяева Марина - Та, что подарила сына [Юлия Вибе, 2022, 128 kbps, MP3]","category":"Художественная литература","subcategory":"[Аудио] Современные любовные романы","torrentSize":"518.7 MB","torrentLink":"magnet:?xt=urn:btih:13B21715F1B6CD3B8C4FFF06CCBE7C380CD6DCB2&tr=http%3A%2F%2Fbt4.t-ru.org%2Fann%3Fmagnet","coverImageUrl":"https://i120.fastpic.org/big/2022/1011/54/1561ead6f6007fafd5aca3e3bf039354.jpg","URL":"https://rutracker.org/forum/viewtopic.php?t=6268928"}
{"name":"Уатт Эрин - Семья Ройалов 4, Отвергнутый наследник [Максим Сергеев, 2022, 64 kbps, MP3]","category":"Художественная литература","subcategory":"[Аудио] Современные любовные романы","torrentSize":"254.1 MB","torrentLink":"magnet:?xt=urn:btih:3EF2658D8BC929EC8B847B698DF1BAE17378D496&tr=http%3A%2F%2Fbt.t-ru.org%2Fann%3Fmagnet","coverImageUrl":"https://i120.fastpic.org/big/2022/1007/91/c0dfb7757b3cc2337de57488caf2c591.jpeg","URL":"https://rutracker.org/forum/viewtopic.php?t=6267345"}
{"name":"Уатт Эрин - Семья Ройалов 3, Разрушенный дворец [Максим Сергеев, 2022, 56 kbps, MP3]","category":"Художественная литература","subcategory":"[Аудио] Современные любовные романы","torrentSize":"252.6 MB","torrentLink":"magnet:?xt=urn:btih:71D417AA2F61C804B97AF31C1124581CB477678E&tr=http%3A%2F%2Fbt3.t-ru.org%2Fann%3Fmagnet","coverImageUrl":"https://i117.fastpic.org/big/2022/0513/d5/4707c82322ec9273ff6718254c7a54d5.jpg","URL":"https://rutracker.org/forum/viewtopic.php?t=6213945"}
{"name":"Шэй Джина - Девушка с пробегом [Ксения Огнева, 2021, 55 kbps, MP3]","category":"Художественная литература","subcategory":"[Аудио] Современные любовные романы","torrentSize":"295 MB","torrentLink":"magnet:?xt=urn:btih:DB01FC5E95BDDDF51A4A58CACFCB7F4068FB672D&tr=http%3A%2F%2Fbt.t-ru.org%2Fann%3Fmagnet","coverImageUrl":"https://i116.fastpic.org/big/2022/0323/a0/0c1dfd6fc2e11aa445c52b2a96bebaa0.jpg","URL":"https://rutracker.org/forum/viewtopic.php?t=6194278"}
{"name":"Джейн Анна – Восхитительная ведьма 1, Восхитительная ведьма [Бриг Инга, 2020, 128 kbps, MP3]","category":"Художественная литература","subcategory":"[Аудио] Современные любовные романы","torrentSize":"858.8 MB","torrentLink":"magnet:?xt=urn:btih:2E01229C03D663E416167C8E1B6CCE84605696F1&tr=http%3A%2F%2Fbt3.t-ru.org%2Fann%3Fmagnet","coverImageUrl":"https://i2.imageban.ru/out/2020/04/17/bc1b69d9a6fd55830674ea0f16e51d6d.jpg","URL":"https://rutracker.org/forum/viewtopic.php?t=5882123"}
{"name":"Делакруз Алекс - Необитаемый остров [Светлана Шаклеина, 2021, 128 kbps, MP3]","category":"Художественная литература","subcategory":"[Аудио] Современные любовные романы","torrentSize":"625.3 MB","torrentLink":"magnet:?xt=urn:btih:8C09C2CC8E14C05B3A3A65E6D50FF2320A32B480&tr=http%3A%2F%2Fbt.t-ru.org%2Fann%3Fmagnet","coverImageUrl":"https://i120.fastpic.org/big/2022/0703/d6/b190115f9912066e26e1d0acded968d6.jpg","URL":"https://rutracker.org/forum/viewtopic.php?t=6231902"}
{"name":"Фрей Эли - Мой лучший враг [Елена Греб, 2018, 128 kbps, MP3]","category":"Художественная литература","subcategory":"[Аудио] Современные любовные романы","torrentSize":"778.7 MB","torrentLink":"magnet:?xt=urn:btih:1C330035D15A19B625F95319C423D6F9B70C030B&tr=http%3A%2F%2Fbt2.t-ru.org%2Fann%3Fmagnet","coverImageUrl":"https://i111.fastpic.ru/big/2020/0412/b1/a0d1c60c1e839ced8755db75ed0c73b1.jpg","URL":"https://rutracker.org/forum/viewtopic.php?t=5880074"}
{"name":"Ручей Наталья – Мой сводный кошмар [Ольга Белова, 2020, 128 kbps, MP3]","category":"Художественная литература","subcategory":"[Аудио] Современные любовные романы","torrentSize":"647.6 MB","torrentLink":"magnet:?xt=urn:btih:1DB4D172B48DD10CF4165F36AB50202DAC9AAE35&tr=http%3A%2F%2Fbt.t-ru.org%2Fann%3Fmagnet","coverImageUrl":"https://i5.imageban.ru/out/2020/11/08/33d97822c5c2d53ab2a3ea275e0a5187.jpg","URL":"https://rutracker.org/forum/viewtopic.php?t=5966218"}
{"name":"Кальби Иман - Она моя 1, Она моя… Книга первая [Аня Грэй, 2021, 128 kbps, MP3]","category":"Художественная литература","subcategory":"[Аудио] Современные любовные романы","torrentSize":"469.1 MB","torrentLink":"magnet:?xt=urn:btih:91B8E53F184C6439E52295B6D9B103708650EF3D&tr=http%3A%2F%2Fbt3.t-ru.org%2Fann%3Fmagnet","coverImageUrl":"https://i116.fastpic.org/big/2021/1126/dd/3ea20d49b06d31f3fb1e0f2fbd37cfdd.jpg","URL":"https://rutracker.org/forum/viewtopic.php?t=6142193"}
{"name":"Д. Алекс – По ту сторону от тебя [Хинрикс Наташа, 2019, 160 kbps, MP3]","category":"Художественная литература","subcategory":"[Аудио] Современные любовные романы","torrentSize":"1.14 GB","torrentLink":"magnet:?xt=urn:btih:46B1DA726B24C567FDD0170187A08CBB9C40725A&tr=http%3A%2F%2Fbt2.t-ru.org%2Fann%3Fmagnet","coverImageUrl":"https://i1.imageban.ru/out/2020/01/21/39be43ab26fbfb10571c5febcca4864e.jpg","URL":"https://rutracker.org/forum/viewtopic.php?t=5838887"}
{"name":"Туманова Анастасия - Полынь – сухие слёзы 2, Сквозь печальные туманы [Елена Понеделина, 2021, 56 kbps, MP3]","category":"Художественная литература","subcategory":"[Аудио] Современные любовные романы","torrentSize":"311.3 MB","torrentLink":"magnet:?xt=urn:btih:349BDD86891A4AA62E4301274A9667298C9DD7E2&tr=http%3A%2F%2Fbt2.t-ru.org%2Fann%3Fmagnet","coverImageUrl":"https://i116.fastpic.org/big/2021/1016/66/0c365d0bf199565345864dad7e9d2366.jpg","URL":"https://rutracker.org/forum/viewtopic.php?t=6123559"}
{"name":"Туманова Анастасия - Полынь – сухие слёзы 1, Разрыв – трава горькая [Елена Понеделина, 2021, 56 kbps, MP3]","category":"Художественная литература","subcategory":"[Аудио] Современные любовные романы","torrentSize":"308 MB","torrentLink":"magnet:?xt=urn:btih:25EB69531C50ED4D4A9EC62ED202C8E4F79A3042&tr=http%3A%2F%2Fbt3.t-ru.org%2Fann%3Fmagnet","coverImageUrl":"https://i116.fastpic.org/big/2021/1016/20/a26fe64f55403514c03d7bb1f7845520.jpg","URL":"https://rutracker.org/forum/viewtopic.php?t=6123525"}
{"name":"Шикова Илона; Еленина Юлия - Ловушки 01, Капкан для бешеного [Галич Ульяна, 2022, 128 kbps, MP3]","category":"Художественная литература","subcategory":"[Аудио] Современные любовные романы","torrentSize":"461.1 MB","torrentLink":"magnet:?xt=urn:btih:73E3332A3C1022E3829B3B1A2454E4527D43DCE1&tr=http%3A%2F%2Fbt4.t-ru.org%2Fann%3Fmagnet","coverImageUrl":"https://i120.fastpic.org/big/2022/0803/78/11438986a5d20e69399f0093b6c11978.jpg","URL":"https://rutracker.org/forum/viewtopic.php?t=6242699"}
{"name":"Кова Дарья – Дневники стюардессы. Часть 1 [Елена Шуйскова, 2020, 128 kbps, MP3]","category":"Художественная литература","subcategory":"[Аудио] Современные любовные романы","torrentSize":"202.7 MB","torrentLink":"magnet:?xt=urn:btih:948C5A66F2D1C9B5F1098D182455D9FCBE7FC788&tr=http%3A%2F%2Fbt2.t-ru.org%2Fann%3Fmagnet","coverImageUrl":"https://i5.imageban.ru/out/2020/11/09/96e272f47fadcfe9c17f05d7107cf1a2.jpg","URL":"https://rutracker.org/forum/viewtopic.php?t=5966538"}
{"name":"Хармель Кристин - Жизнь, которая не стала моей [Васильева Марианна, 2021, 56 kbps, MP3]","category":"Художественная литература","subcategory":"[Аудио] Современные любовные романы","torrentSize":"252.2 MB","torrentLink":"magnet:?xt=urn:btih:CB9A63F9F35D7BE690FA12CFF21CE26D31D80B46&tr=http%3A%2F%2Fbt3.t-ru.org%2Fann%3Fmagnet","coverImageUrl":"https://i115.fastpic.ru/big/2021/0718/39/3d8f2c96fd0169781872e1113a200f39.jpg","URL":"https://rutracker.org/forum/viewtopic.php?t=6082789"}
{"name":"Гувер Колин - Уродливая любовь [Ксения Бржезовская, Юлия Бочанова, Юрий Кузаков, 2021, 128 kbps, MP3]","category":"Художественная литература","subcategory":"[Аудио] Современные любовные романы","torrentSize":"445.3 MB","torrentLink":"magnet:?xt=urn:btih:B807957FDB6E85D12847DC21657F310282219405&tr=http%3A%2F%2Fbt3.t-ru.org%2Fann%3Fmagnet","coverImageUrl":"https://i115.fastpic.ru/big/2021/0624/4f/d9118cb9ecee60593ecac3e9dd45b94f.jpg","URL":"https://rutracker.org/forum/viewtopic.php?t=6072601"}
{"name":"Рымарь Диана - Сапфировые истории 5, Две по цене одной [Човжик Алла, 2021, 128 kbps, MP3]","category":"Художественная литература","subcategory":"[Аудио] Современные любовные романы","torrentSize":"464 MB","torrentLink":"magnet:?xt=urn:btih:D654BECF6D741B04DBA817B76054ECED59D60AE6&tr=http%3A%2F%2Fbt.t-ru.org%2Fann%3Fmagnet","coverImageUrl":"https://i114.fastpic.ru/big/2021/0511/8e/572345b2d16ee6e02bec4966a9b07f8e.jpg","URL":"https://rutracker.org/forum/viewtopic.php?t=6053249"}
{"name":"Рымарь Диана - Сапфировые истории 10, (Не) моя свадьба [Алла Човжик, 2022, 128 kbps, MP3]","category":"Художественная литература","subcategory":"[Аудио] Современные любовные романы","torrentSize":"513.5 MB","torrentLink":"magnet:?xt=urn:btih:5EC70CB302B1ABE31A05754AC50FD8FD480FE813&tr=http%3A%2F%2Fbt4.t-ru.org%2Fann%3Fmagnet","coverImageUrl":"https://i120.fastpic.org/big/2022/0926/6f/7286c3ae0df9bce23a16b6a426cf8b6f.jpg","URL":"https://rutracker.org/forum/viewtopic.php?t=6262853"}
{"name":"Резник Юлия - Домы 1, Кукушка [Полина Васильчук, 2022, 112 kbps, MP3]","category":"Художественная литература","subcategory":"[Аудио] Современные любовные романы","torrentSize":"408.9 MB","torrentLink":"magnet:?xt=urn:btih:CFC66F81E89016581E6B333B7F0A610275C3B73E&tr=http%3A%2F%2Fbt4.t-ru.org%2Fann%3Fmagnet","coverImageUrl":"https://i120.fastpic.org/big/2022/1017/81/15d2065849809ebeea316e11b452d981.jpg","URL":"https://rutracker.org/forum/viewtopic.php?t=6271449"}
{"name":"Novela - Одержимость 1, Покоряясь тебе [Ольга Струна, 2022, 128 kbps, MP3]","category":"Художественная литература","subcategory":"[Аудио] Современные любовные романы","torrentSize":"1.16 GB","torrentLink":"magnet:?xt=urn:btih:5DBCB8275B6EBB71FFA33358CDDA72AF583BF3E5&tr=http%3A%2F%2Fbt3.t-ru.org%2Fann%3Fmagnet","coverImageUrl":"https://i120.fastpic.org/big/2022/1016/5d/64e3badb56e7c346841aaeb858000e5d.jpg","URL":"https://rutracker.org/forum/viewtopic.php?t=6271026"}
{"name":"Есаулкова Ольга; Кривошлыкова Светлана; и др. - Выбор Евы. Гастрольные истории. Любовь — тональность ля минор [Новикова Нелли, 2021, 56 kbps, MP3]","category":"Художественная литература","subcategory":"[Аудио] Современные любовные романы","torrentSize":"179 MB","torrentLink":"magnet:?xt=urn:btih:353BFFE88B9CF19CE65871FD506ACBCB34139F11&tr=http%3A%2F%2Fbt3.t-ru.org%2Fann%3Fmagnet","coverImageUrl":"https://i120.fastpic.org/big/2022/1016/dc/6671cc3b5935d6de6bc4f775f6fe27dc.jpg","URL":"https://rutracker.org/forum/viewtopic.php?t=6270962"}
{"name":"Колган Дженни Т. - Встретимся в кафе «Капкейк» [Алла Човжик, 2021, 56 kbps, MP3]","category":"Художественная литература","subcategory":"[Аудио] Современные любовные романы","torrentSize":"342.5 MB","torrentLink":"magnet:?xt=urn:btih:E86EB4F699DA69DCC96EC3EDD3FE480D25B838E8&tr=http%3A%2F%2Fbt.t-ru.org%2Fann%3Fmagnet","coverImageUrl":"https://i116.fastpic.org/big/2021/1031/9c/a6530d6c4397aba43348cabb4452719c.jpg","URL":"https://rutracker.org/forum/viewtopic.php?t=6130229"}
{"name":"Мойес Джоджо - Серебристая бухта [Алла Човжик, 2022, 64 kbps, MP3]","category":"Художественная литература","subcategory":"[Аудио] Современные любовные романы","torrentSize":"397 MB","torrentLink":"magnet:?xt=urn:btih:9B2FC7839CA46715B79DF213671269F05FF6EC8D&tr=http%3A%2F%2Fbt2.t-ru.org%2Fann%3Fmagnet","coverImageUrl":"https://i120.fastpic.org/big/2022/0626/40/f78e97b60785d9f3cc4624a4dbc60940.jpg","URL":"https://rutracker.org/forum/viewtopic.php?t=6229962"}
{"name":"Колган Дженни Т. – Летний ресторанчик на берегу [Човжик Алла, 2020, 64 kbps, MP3]","category":"Художественная литература","subcategory":"[Аудио] Современные любовные романы","torrentSize":"266.4 MB","torrentLink":"magnet:?xt=urn:btih:9DF6EB33FB3A19A5F33FE0A4D17B1450681B1B9C&tr=http%3A%2F%2Fbt.t-ru.org%2Fann%3Fmagnet","coverImageUrl":"https://i3.imageban.ru/out/2020/09/16/5ae8478038aa874e23e090925cb7bb25.jpg","URL":"https://rutracker.org/forum/viewtopic.php?t=5942409"}
{"name":"Лель Агата - Интим не предлагать! [Чураченко Ирина, 2021, 128 kbps, MP3]","category":"Художественная литература","subcategory":"[Аудио] Современные любовные романы","torrentSize":"393 MB","torrentLink":"magnet:?xt=urn:btih:B8CCA94332C54C7A5719C524BC94114C2C639280&tr=http%3A%2F%2Fbt.t-ru.org%2Fann%3Fmagnet","coverImageUrl":"https://i114.fastpic.ru/big/2021/0510/33/230fb4cbe268a93eb42d3417af052233.jpg","URL":"https://rutracker.org/forum/viewtopic.php?t=6052676"}
{"name":"Макнамара Эли - Магазинчик счастья Кейт и Клары [Дина Бобылёва, 2021, 128 kbps, MP3]","category":"Художественная литература","subcategory":"[Аудио] Современные любовные романы","torrentSize":"534.2 MB","torrentLink":"magnet:?xt=urn:btih:DFBE0BD96179616FEEF97BE1763C50A2F6ED04EF&tr=http%3A%2F%2Fbt2.t-ru.org%2Fann%3Fmagnet","coverImageUrl":"https://i116.fastpic.org/big/2022/0205/50/f9ba796a80360fac546c4f086cbcd850.jpg","URL":"https://rutracker.org/forum/viewtopic.php?t=6174361"}
{"name":"Кван Кевин - Секс и тщеславие [Човжик Алла, 2021, 64 kbps, MP3]","category":"Художественная литература","subcategory":"[Аудио] Современные любовные романы","torrentSize":"252.9 MB","torrentLink":"magnet:?xt=urn:btih:98066860D95DB0458E10F6EBE4B47A82AE592ADC&tr=http%3A%2F%2Fbt4.t-ru.org%2Fann%3Fmagnet","coverImageUrl":"https://i114.fastpic.ru/big/2021/0606/04/ee1730e4d1f2a9ed610979e47f247e04.jpg","URL":"https://rutracker.org/forum/viewtopic.php?t=6064913"}
{"name":"Вильмонт Екатерина - Девственная селедка [Винокурова Надежда, 2010 г., 96 kbps, MP3]","category":"Художественная литература","subcategory":"[Аудио] Современные любовные романы","torrentSize":"234 MB","torrentLink":"magnet:?xt=urn:btih:FF2608094F0CCE7839EECBDC927AE27428FC4620&tr=http%3A%2F%2Fbt3.t-ru.org%2Fann%3Fmagnet","coverImageUrl":"http://www.10pix.ru/img1/3096/2903559.jpg","URL":"https://rutracker.org/forum/viewtopic.php?t=3295832"}
{"name":"Вильмонт Екатерина - Мимолётности, или Подумаешь, бином Ньютона! [Винокурова Надежда, 2011, 96 kbps, MP3]","category":"Художественная литература","subcategory":"[Аудио] Современные любовные романы","torrentSize":"246.4 MB","torrentLink":"magnet:?xt=urn:btih:32A9925F8D126AC5EC9752F5D4071560BAEF3520&tr=http%3A%2F%2Fbt4.t-ru.org%2Fann%3Fmagnet","coverImageUrl":"http://s006.radikal.ru/i213/1111/69/1c69208004f7.jpg","URL":"https://rutracker.org/forum/viewtopic.php?t=3832792"}
{"name":"Вильмонт Екатерина - Со всей дури! [Ксения Бржезовская, 2015 г., 128 kbps, MP3]","category":"Художественная литература","subcategory":"[Аудио] Современные любовные романы","torrentSize":"349.4 MB","torrentLink":"magnet:?xt=urn:btih:D86E50B535F81EF95E2D1C48CA21BE085960338E&tr=http%3A%2F%2Fbt4.t-ru.org%2Fann%3Fmagnet","coverImageUrl":"http://i65.fastpic.ru/big/2015/0904/af/1becd0e412f8d855a1ecfcda44c341af.jpg","URL":"https://rutracker.org/forum/viewtopic.php?t=5072890"}
{"name":"Вильмонт Екатерина - Фиг ли нам, красивым дамам! [Галина Чигинская, 2016 г., 128 kbps, MP3]","category":"Художественная литература","subcategory":"[Аудио] Современные любовные романы","torrentSize":"310.9 MB","torrentLink":"magnet:?xt=urn:btih:C8FCCBC74DEC791D2618A3606ECDFE2A5425E4DF&tr=http%3A%2F%2Fbt3.t-ru.org%2Fann%3Fmagnet","coverImageUrl":"http://i75.fastpic.ru/big/2016/0204/5c/e617adf89a2acf15f13418d861462d5c.jpg","URL":"https://rutracker.org/forum/viewtopic.php?t=5164632"}
{"name":"Вильмонт Екатерина - Девочка с перчиками [Ненарокомова Татьяна, 2015 г., 96 kbps, MP3]","category":"Художественная литература","subcategory":"[Аудио] Современные любовные романы","torrentSize":"300.9 MB","torrentLink":"magnet:?xt=urn:btih:48AF2C1E1EE3EF16B157061270F384C8216151A4&tr=http%3A%2F%2Fbt3.t-ru.org%2Fann%3Fmagnet","coverImageUrl":"http://s017.radikal.ru/i430/1603/37/8bc848993113.jpg","URL":"https://rutracker.org/forum/viewtopic.php?t=5197302"}
{"name":"Вильмонт Екатерина - Сплошная лебедянь! [Елена Дельвер, 2016, 128 kbps, MP3]","category":"Художественная литература","subcategory":"[Аудио] Современные любовные романы","torrentSize":"335.2 MB","torrentLink":"magnet:?xt=urn:btih:E40684B5836F5722EF8F4C601171346715560770&tr=http%3A%2F%2Fbt.t-ru.org%2Fann%3Fmagnet","coverImageUrl":"http://s019.radikal.ru/i627/1610/ae/307bedac8447.jpg","URL":"https://rutracker.org/forum/viewtopic.php?t=5298589"}
{"name":"Вильмонт Екатерина - А я дура пятая! [Ксения Бржезовская, 2017, 256 kbps, MP3]","category":"Художественная литература","subcategory":"[Аудио] Современные любовные романы","torrentSize":"613.5 MB","torrentLink":"magnet:?xt=urn:btih:ECE5434740F81FEE495E37BE6C6E51C1EBF0BD37&tr=http%3A%2F%2Fbt3.t-ru.org%2Fann%3Fmagnet","coverImageUrl":"http://i91.fastpic.ru/big/2017/0309/fe/a562c08c2a093cc411a4a61531e538fe.jpg","URL":"https://rutracker.org/forum/viewtopic.php?t=5369745"}
{"name":"Толстой Алексей - Иоанн Дамаскин [Георгий Корольчук, 2004, 64 kbps, MP3]","category":"Художественная литература","subcategory":"[Аудио] Поэзия","torrentSize":"21.1 MB","torrentLink":"magnet:?xt=urn:btih:5768659D49AF97B25ADD20B9B22F76C67881A17C&tr=http%3A%2F%2Fbt.t-ru.org%2Fann%3Fmagnet","coverImageUrl":"https://i114.fastpic.ru/big/2021/0127/8a/cdd9f56196487c02f3e7d76258dce28a.jpg","URL":"https://rutracker.org/forum/viewtopic.php?t=6002712"}
{"name":"Бальмонт Константин - Только любовь. Семицветник [Ольга Голованова, 2020, 128 kbps, MP3]","category":"Художественная литература","subcategory":"[Аудио] Поэзия","torrentSize":"131.3 MB","torrentLink":"magnet:?xt=urn:btih:74D6FD497243B445B1C00C29A1F9DA3914244D16&tr=http%3A%2F%2Fbt4.t-ru.org%2Fann%3Fmagnet","coverImageUrl":"https://i114.fastpic.ru/big/2021/0602/0c/c4e50d60b187c653b59b58635679f90c.jpg","URL":"https://rutracker.org/forum/viewtopic.php?t=6063403"}
{"name":"Бальмонт Константин - Восхождение, Я неземной. Музыкально-поэтические композиции [Nikosho, 2001 г., VBR 100, MP3]","category":"Художественная литература","subcategory":"[Аудио] Поэзия","torrentSize":"75.5 MB","torrentLink":"magnet:?xt=urn:btih:ACFF3517C55FD8B23821C2C639591C368E0793B2&tr=http%3A%2F%2Fbt3.t-ru.org%2Fann%3Fmagnet","coverImageUrl":"http://i17.fastpic.ru/big/2011/0307/e4/62ba573f815b0b923b5bcb12ec7ce0e4.jpg","URL":"https://rutracker.org/forum/viewtopic.php?t=3463885"}
{"name":"Анненский Иннокентий Федорович, Ахматова Анна Андреевна, Бальмонт Константин Дмитриевич, Белый Андрей, Блок Александр Александрович, и др. - Поэзия Серебряного века [Плотников Борис,Бабенко Алёна,Егоров Виталий, и др. 2009 г., 256 kbps, MP3]","category":"Художественная литература","subcategory":"[Аудио] Поэзия","torrentSize":"680.1 MB","torrentLink":"magnet:?xt=urn:btih:2DAF1A757CBB53CEEE85C67B5219311DDE6939BE&tr=http%3A%2F%2Fbt4.t-ru.org%2Fann%3Fmagnet","coverImageUrl":"http://i63.fastpic.ru/big/2014/0702/88/2da552c38f7f2ca66f9233b0c1e5ef88.jpg","URL":"https://rutracker.org/forum/viewtopic.php?t=4774764"}
{"name":"По Эдгар Аллан - Ворон. Стихотворения и поэмы в переводах В. Брюсова и К. Бальмонта [Виталий Толубеев, 2010 г., 160 kbps, MP3]","category":"Художественная литература","subcategory":"[Аудио] Поэзия","torrentSize":"637.6 MB","torrentLink":"magnet:?xt=urn:btih:494734EA27D24865310CC22ED641F71E50FA43D6&tr=http%3A%2F%2Fbt3.t-ru.org%2Fann%3Fmagnet","coverImageUrl":"http://i12.fastpic.ru/big/2010/1123/6b/b10106568fa2577218b41acb8dad256b.jpg","URL":"https://rutracker.org/forum/viewtopic.php?t=3277793"}
{"name":"И. Анненский, К. Бальмонт, З. Гиппиус, В. Брюсов, А. Белый, Н.Клюев, Н. Гумилев, И. Северянин, А. Ахматова, О. Мандельштам, М. Цветаева - Поэзия серебряного века [Александр Андриенко, Наталья Михеева, 2008, 64 kbps]","category":"Художественная литература","subcategory":"[Аудио] Поэзия","torrentSize":"120.4 MB","torrentLink":"magnet:?xt=urn:btih:ED81243DA07DB5F853A276FC654EA4D2E859857E&tr=http%3A%2F%2Fbt3.t-ru.org%2Fann%3Fmagnet","coverImageUrl":"http://i3.fastpic.ru/big/2009/1023/8d/e98a6674d8aadf313fc875888b36418d.jpg","URL":"https://rutracker.org/forum/viewtopic.php?t=1842324"}
{"name":"Иван Бунин - Стихи, лирика [Александр Котов, 2004, 192 кбит/с]","category":"Художественная литература","subcategory":"[Аудио] Поэзия","torrentSize":"51 MB","torrentLink":"magnet:?xt=urn:btih:DFBA2D23C5D9A8C6D31294FFB1A06DAD2FF69BBC&tr=http%3A%2F%2Fbt.t-ru.org%2Fann%3Fmagnet","URL":"https://rutracker.org/forum/viewtopic.php?t=247025"}
{"name":"Классики и современники- А.С.Пушкин, А.Тарковский, Б.Ахмадулина, Б.Пастернак, В.Брюсов, В.ГюгоД.Китс, И.Бунин и др. - Стихотворения и поэмы. Часть 1 [Б.Фрейндлих, А.Садовская, А.Мальцева, В.Попов, И.Смоктуновский и др. 2008, 96 kbps или лучше]","category":"Художественная литература","subcategory":"[Аудио] Поэзия","torrentSize":"575.5 MB","torrentLink":"magnet:?xt=urn:btih:9AEB134B78BCC7CB49CEB030E12024E5BEBEB80A&tr=http%3A%2F%2Fbt4.t-ru.org%2Fann%3Fmagnet","URL":"https://rutracker.org/forum/viewtopic.php?t=2312592"}
{"name":"Мандельштам Осип - Я вернулся в мой город [Рафаэль Клейнер, 1990, 256 kbps, MP3]","category":"Художественная литература","subcategory":"[Аудио] Поэзия","torrentSize":"81 MB","torrentLink":"magnet:?xt=urn:btih:38DA691AB1C99FBFC906708DDBD283CFE3AE2C8B&tr=http%3A%2F%2Fbt4.t-ru.org%2Fann%3Fmagnet","coverImageUrl":"https://m.media-amazon.com/images/I/91oojRxSYFL._SS500_.jpg","URL":"https://rutracker.org/forum/viewtopic.php?t=6146851"}
{"name":"Бунин Иван - Стихи [Илья Хвост, (ЛИ), 2014 г., 128 kbps, MP3]","category":"Художественная литература","subcategory":"[Аудио] Поэзия","torrentSize":"17.2 MB","torrentLink":"magnet:?xt=urn:btih:345175BDF1C485B4EF911230A50A89D91897C859&tr=http%3A%2F%2Fbt3.t-ru.org%2Fann%3Fmagnet","coverImageUrl":"http://i67.fastpic.ru/big/2014/1222/d2/ae63409cf5e7e2385f239e670861bbd2.png","URL":"https://rutracker.org/forum/viewtopic.php?t=4896149"}
{"name":"Пушкин Александр, Барков Иван - Поэзия русского эроса [Михаил Горевой, 2014 г., 320 kbps, MP3]","category":"Художественная литература","subcategory":"[Аудио] Поэзия","torrentSize":"274.2 MB","torrentLink":"magnet:?xt=urn:btih:882820E1B8B08FE09DA5709D82E8CC416F15AE07&tr=http%3A%2F%2Fbt.t-ru.org%2Fann%3Fmagnet","coverImageUrl":"http://i33.fastpic.ru/big/2014/0319/7c/6360a4589db95f98e5b997d18cd2b17c.jpg","URL":"https://rutracker.org/forum/viewtopic.php?t=4696831"}
{"name":"Аполлинер Гийом - Стихи. Сборник [Прудовский Илья, 2009, 96 kbps]","category":"Художественная литература","subcategory":"[Аудио] Поэзия","torrentSize":"322.9 MB","torrentLink":"magnet:?xt=urn:btih:B7137EB7F978779C743D42CF9B298872A4DB5970&tr=http%3A%2F%2Fbt4.t-ru.org%2Fann%3Fmagnet","coverImageUrl":"http://i051.radikal.ru/0912/62/b0d53f3044c4.jpg","URL":"https://rutracker.org/forum/viewtopic.php?t=2659476"}
{"name":"Арсений Тарковский, стихи, читает автор [VBR 192-320 kbps]","category":"Художественная литература","subcategory":"[Аудио] Поэзия","torrentSize":"74 MB","torrentLink":"magnet:?xt=urn:btih:9BD8AF35E0B32C5F61B8D800D017FCFEBFE32E94&tr=http%3A%2F%2Fbt3.t-ru.org%2Fann%3Fmagnet","coverImageUrl":"http://pic.ipicture.ru/uploads/090725/e3TiAB1B33.jpg","URL":"https://rutracker.org/forum/viewtopic.php?t=2043985"}
{"name":"Цветаева Марина Ивановна - Мне нравится, что Вы больны не мной… (сборник) - (Русская классика (Эксмо)) [Елизавета Егорова, 2019, 128 kbps, MP3]","category":"Художественная литература","subcategory":"[Аудио] Поэзия","torrentSize":"1.15 GB","torrentLink":"magnet:?xt=urn:btih:077DE1035D66E8F4825098DCAA63DEFC105CD600&tr=http%3A%2F%2Fbt.t-ru.org%2Fann%3Fmagnet","coverImageUrl":"http://images.vfl.ru/ii/1578854688/1b587d42/29183986.jpg","URL":"https://rutracker.org/forum/viewtopic.php?t=5834305"}
{"name":"Пушкин А.С. - Руслан и Людмила [Николай Мортон, 28-34 kbps]","category":"Художественная литература","subcategory":"[Аудио] Поэзия","torrentSize":"31.7 MB","torrentLink":"magnet:?xt=urn:btih:31E3CCDBBC1627EB75FEC5A343291458D79B7518&tr=http%3A%2F%2Fbt4.t-ru.org%2Fann%3Fmagnet","coverImageUrl":"http://www.10pix.ru/img1/4450/729420.jpg","URL":"https://rutracker.org/forum/viewtopic.php?t=2515002"}
{"name":"Пушкин Александр Сергеевич - поэма Руслан и Людмила [Елена Хайдурова (ЛИ) , 2012 г., 128, MP3]","category":"Художественная литература","subcategory":"[Аудио] Поэзия","torrentSize":"168.3 MB","torrentLink":"magnet:?xt=urn:btih:C426DEE0A26E03561F152AED567FB263F95EC2A8&tr=http%3A%2F%2Fbt2.t-ru.org%2Fann%3Fmagnet","coverImageUrl":"http://s018.radikal.ru/i508/1202/4f/030ed4f6de6b.jpg","URL":"https://rutracker.org/forum/viewtopic.php?t=3928966"}
{"name":"Стус Василий - Цветок на камне (стихотворения разных лет) [Ольга Бойцова, Анна Литкенс, Ольга Тенякова, Тимофей Трибунцев, 2012 г., 320 kbps, MP3]","category":"Художественная литература","subcategory":"[Аудио] Поэзия","torrentSize":"120.1 MB","torrentLink":"magnet:?xt=urn:btih:DC9D3870A74813442E46316435C5CD54AACEA126&tr=http%3A%2F%2Fbt2.t-ru.org%2Fann%3Fmagnet","coverImageUrl":"http://i55.fastpic.ru/big/2014/0502/24/8257e2a6642ae66b7e9a3b1cee63a024.jpg","URL":"https://rutracker.org/forum/viewtopic.php?t=4730269"}
{"name":"Ямпольский Вадим - Будешь ли скучать по мне? [Ямпольский Вадим, (ЛИ), 2022, 320 kbps, MP3]","category":"Художественная литература","subcategory":"[Аудио] Поэзия","torrentSize":"8.8 MB","torrentLink":"magnet:?xt=urn:btih:A5B64693E6AB26D3E74EB6C496554430F12DD450&tr=http%3A%2F%2Fbt4.t-ru.org%2Fann%3Fmagnet","coverImageUrl":"https://i120.fastpic.org/big/2022/1016/1e/517d513ba44f76eac0b4db484087c21e.jpg","URL":"https://rutracker.org/forum/viewtopic.php?t=6271024"}
{"name":"Маяковский Владимир - Избранное [Вениамин Смехов, 2007 г., 32 kbps, MP3]","category":"Художественная литература","subcategory":"[Аудио] Поэзия","torrentSize":"35.6 MB","torrentLink":"magnet:?xt=urn:btih:1497DEB9BFFF858C6A9A95939E20C8AC6B2D9822&tr=http%3A%2F%2Fbt3.t-ru.org%2Fann%3Fmagnet","coverImageUrl":"http://i12.fastpic.ru/big/2010/1122/70/b2e8623122c2569276f722f8a518ef70.jpg","URL":"https://rutracker.org/forum/viewtopic.php?t=3277373"}
{"name":"Сергей Есенин - Родина (Литературно - музыкальная композиция) [Алексей Покровский, 1976 г., 320 kbps, MP3]","category":"Художественная литература","subcategory":"[Аудио] Поэзия","torrentSize":"123.6 MB","torrentLink":"magnet:?xt=urn:btih:61DDC52D64319A48D59E192C887F73CCFBD93FCA&tr=http%3A%2F%2Fbt3.t-ru.org%2Fann%3Fmagnet","coverImageUrl":"http://i58.fastpic.ru/big/2014/0209/e3/028f776e79b359df6e7d55a3481cb2e3.jpg","URL":"https://rutracker.org/forum/viewtopic.php?t=4665540"}
{"name":"Тютчев Фёдор: «Нам не дано предугадать...» [2008, Самойлов В., 192 kbps]","category":"Художественная литература","subcategory":"[Аудио] Поэзия","torrentSize":"159.1 MB","torrentLink":"magnet:?xt=urn:btih:CB798B35FA7DBD348441773626DADAC7AA169F49&tr=http%3A%2F%2Fbt.t-ru.org%2Fann%3Fmagnet","coverImageUrl":"http://i33.fastpic.ru/big/2014/0212/10/6b45971deea97c58fb0e5fc0c3707b10.jpg","URL":"https://rutracker.org/forum/viewtopic.php?t=4667415"}
{"name":"Слово о полку Игореве [Д.С.Лихачев, Олег Табаков, 2011 г., 125-148 kbps, MP3]","category":"Художественная литература","subcategory":"[Аудио] Поэзия","torrentSize":"87 MB","torrentLink":"magnet:?xt=urn:btih:4D60FD2EF5638EA2AFFD9492B9F06416A7ECA7F1&tr=http%3A%2F%2Fbt.t-ru.org%2Fann%3Fmagnet","coverImageUrl":"http://i29.fastpic.ru/big/2011/1210/29/1c544444843d41cd9cd914960a0b0229.jpg","URL":"https://rutracker.org/forum/viewtopic.php?t=3855549"}
{"name":"Хайям Омар - Рубаи [Сергей Шакуров, 2013, 128 kbps, MP3]","category":"Художественная литература","subcategory":"[Аудио] Поэзия","torrentSize":"127.5 MB","torrentLink":"magnet:?xt=urn:btih:C6A0961DE427E468DD24948D241F67A9EC41B19D&tr=http%3A%2F%2Fbt.t-ru.org%2Fann%3Fmagnet","coverImageUrl":"http://images.vfl.ru/ii/1610359861/0d8b79c3/32915834.jpg","URL":"https://rutracker.org/forum/viewtopic.php?t=5995501"}
{"name":"Пушкин А.С. Евгений Онегин [Иннокентий Смоктуновский, 2005, 192 kbps]","category":"Художественная литература","subcategory":"[Аудио] Поэзия","torrentSize":"435 MB","torrentLink":"magnet:?xt=urn:btih:EC2D17F9E0634BCC8D5ACD28C498F1DE30FE5BF6&tr=http%3A%2F%2Fbt3.t-ru.org%2Fann%3Fmagnet","coverImageUrl":"http://pic.ipicture.ru/uploads/090627/thumbs/NOgrkWaSSx.jpg","URL":"https://rutracker.org/forum/viewtopic.php?t=1967722"}
{"name":"Мильтон Джон - Потерянный рай [Прудовский Илья, 2011 г. 192 kbps, MP3]","category":"Художественная литература","subcategory":"[Аудио] Поэзия","torrentSize":"1.23 GB","torrentLink":"magnet:?xt=urn:btih:5D9674DDC19D95D655230D8D492DD71067ACE265&tr=http%3A%2F%2Fbt3.t-ru.org%2Fann%3Fmagnet","coverImageUrl":"http://i53.fastpic.ru/big/2013/0302/c2/36b77441093768cd7b17718f966a80c2.jpg","URL":"https://rutracker.org/forum/viewtopic.php?t=4366258"}
{"name":"Пушкин Александр - Евгений Онегин [Смоктуновский Иннокентий, Мелодия 2008, 128 kbps, MP3]","category":"Художественная литература","subcategory":"[Аудио] Поэзия","torrentSize":"277.7 MB","torrentLink":"magnet:?xt=urn:btih:73C245D34D14DA665E657F02E26EE2C11C3E94E3&tr=http%3A%2F%2Fbt4.t-ru.org%2Fann%3Fmagnet","coverImageUrl":"http://a.radikal.ru/a13/1901/d6/48cc878b24ab.jpg","URL":"https://rutracker.org/forum/viewtopic.php?t=5681133"}
{"name":"Уильям Шекспир - Сонеты [Родион Приходько, 2008, 128 kbps]","category":"Художественная литература","subcategory":"[Аудио] Поэзия","torrentSize":"159.6 MB","torrentLink":"magnet:?xt=urn:btih:38739E9A54A3391CB43937F30CA9859707D8BFAF&tr=http%3A%2F%2Fbt3.t-ru.org%2Fann%3Fmagnet","coverImageUrl":"http://img.express-kniga.com/A51220.jpg","URL":"https://rutracker.org/forum/viewtopic.php?t=2070504"}
{"name":"Уильям Шекспир - Сонеты Шекспира в переводах С. Маршака [Самойлов Владимир, 2013 г., 96 kbps, MP3]","category":"Художественная литература","subcategory":"[Аудио] Поэзия","torrentSize":"146.8 MB","torrentLink":"magnet:?xt=urn:btih:461C689AB361B12D4AF84717494E914E6D379F1A&tr=http%3A%2F%2Fbt3.t-ru.org%2Fann%3Fmagnet","coverImageUrl":"http://i57.fastpic.ru/big/2014/0329/a2/50bda07fbce1ca95adaf0949d0580ea2.jpg","URL":"https://rutracker.org/forum/viewtopic.php?t=4704636"}
{"name":"Шекспир Уильям - Сонеты [Иннокентий Смоктуновский, 2020, 128 kbps, MP3]","category":"Художественная литература","subcategory":"[Аудио] Поэзия","torrentSize":"47.8 MB","torrentLink":"magnet:?xt=urn:btih:FB7DCD32BB6A60C200876643121B6998C0E36143&tr=http%3A%2F%2Fbt.t-ru.org%2Fann%3Fmagnet","coverImageUrl":"http://gallery.abook-club.ru/var/albums/covers/audiobook-6/Soneti_by_Smoktunovskij.jpg","URL":"https://rutracker.org/forum/viewtopic.php?t=6019465"}
{"name":"Есенин Сергей - Д. Быков читает. (Лекция + книга), Страна негодяев [Быков Дмитрий, 2019, 56 kbps, MP3]","category":"Художественная литература","subcategory":"[Аудио] Поэзия","torrentSize":"53.4 MB","torrentLink":"magnet:?xt=urn:btih:7A87BF843F2A605C4D3BB8D6B982FE12F7DADF17&tr=http%3A%2F%2Fbt.t-ru.org%2Fann%3Fmagnet","coverImageUrl":"https://i114.fastpic.ru/big/2021/0531/35/e47bf7ea2d82e844b966764130d3af35.jpg","URL":"https://rutracker.org/forum/viewtopic.php?t=6062414"}
{"name":"Шекспир Уильям - Сонеты [Сергей Юрский, 2021, 128 kbps, MP3]","category":"Художественная литература","subcategory":"[Аудио] Поэзия","torrentSize":"29.8 MB","torrentLink":"magnet:?xt=urn:btih:A9A4D84B855F28049D020D9E5CA7716974577C6F&tr=http%3A%2F%2Fbt2.t-ru.org%2Fann%3Fmagnet","coverImageUrl":"https://i114.fastpic.ru/big/2021/0302/9b/0614561eee2a7d8df413311c1919e39b.jpg","URL":"https://rutracker.org/forum/viewtopic.php?t=6019546"}
{"name":"Бальмонт Константин, Брюсов Валерий - Страницы русской поэзии XVIII-XX в.в. [А. Кутепов, В. Маратов, И. Смоктуновский, 1981, 256 kbps, MP3]","category":"Художественная литература","subcategory":"[Аудио] Поэзия","torrentSize":"92 MB","torrentLink":"magnet:?xt=urn:btih:605159E0485A65A7C3F4FAEDBB779FD5F3FA3192&tr=http%3A%2F%2Fbt3.t-ru.org%2Fann%3Fmagnet","coverImageUrl":"https://i116.fastpic.org/big/2021/1213/2e/3bf81809bf96c98c55262348fe93352e.jpg","URL":"https://rutracker.org/forum/viewtopic.php?t=6150100"}
{"name":"Анна Ахматова \"Стихи\" [А.Ахматова, 32 кбит/с]","category":"Художественная литература","subcategory":"[Аудио] Поэзия","torrentSize":"19.9 MB","torrentLink":"magnet:?xt=urn:btih:008CE518F33A4AFCF2BA52D574132DB9971290D8&tr=http%3A%2F%2Fbt.t-ru.org%2Fann%3Fmagnet","coverImageUrl":"http://www.hotcd.ru/scr/img/12405_0-0-120-1.jpg","URL":"https://rutracker.org/forum/viewtopic.php?t=38394"}
{"name":"По Эдгар Аллан - Ворон [Станишевский Николай, (ЛИ), 2009 г., 128 kbps, MP3]","category":"Художественная литература","subcategory":"[Аудио] Поэзия","torrentSize":"8.1 MB","torrentLink":"magnet:?xt=urn:btih:2F82C6EC168B28252D15E550C3C1CDF8032D9AE1&tr=http%3A%2F%2Fbt.t-ru.org%2Fann%3Fmagnet","coverImageUrl":"https://i111.fastpic.ru/big/2020/0218/56/0043e5fb2661d234a7396716518f8656.jpg","URL":"https://rutracker.org/forum/viewtopic.php?t=5852772"}
